<?xml version="1.0" encoding="ISO-8859-1"?>
<modeling>
 <generator>
  <i name="program" type="string">vasp </i>
  <i name="version" type="string">5.3.5  </i>
  <i name="subversion" type="string">31Mar14 (build Jun 20 2014 13:15:13) complex                          parallel </i>
  <i name="platform" type="string">LinuxIFC </i>
  <i name="date" type="string">2025 12 16 </i>
  <i name="time" type="string">16:09:44 </i>
 </generator>
 <incar>
  <i type="string" name="PREC">accurate</i>
  <i type="int" name="IALGO">    68</i>
  <i type="logical" name="ADDGRID"> T  </i>
  <i type="int" name="NELM">   100</i>
  <i type="int" name="NELMIN">     4</i>
  <i type="int" name="IBRION">     2</i>
  <i name="EDIFF">      0.00000100</i>
  <i name="EDIFFG">     -0.02000000</i>
  <i type="int" name="NSW">    30</i>
  <i type="int" name="ISIF">     3</i>
  <i name="ENCUT">    600.00000000</i>
  <i type="logical" name="LREAL"> F  </i>
  <i type="int" name="ISMEAR">     0</i>
  <i name="SIGMA">      0.10000000</i>
  <i type="logical" name="LWAVE"> F  </i>
  <i type="logical" name="LCHARG"> F  </i>
  <i type="int" name="NELM">   100</i>
 </incar>
 <kpoints>
  <generation param="Auto">
   <i name="subdivisionlength">     20.00000000 </i>
   <v type="int" name="divisions">       4        4        4 </v>
   <v name="usershift">      0.00000000       0.00000000       0.00000000 </v>
   <v name="genvec1">      0.25000000       0.00000000       0.00000000 </v>
   <v name="genvec2">      0.00000000       0.25000000       0.00000000 </v>
   <v name="genvec3">      0.00000000       0.00000000       0.25000000 </v>
   <v name="shift">      0.00000000       0.00000000       0.00000000 </v>
  </generation>
  <varray name="kpointlist" >
   <v>       0.00000000       0.00000000       0.00000000 </v>
   <v>       0.25000000       0.00000000       0.00000000 </v>
   <v>       0.50000000       0.00000000       0.00000000 </v>
   <v>       0.00000000       0.25000000       0.00000000 </v>
   <v>       0.25000000       0.25000000       0.00000000 </v>
   <v>       0.50000000       0.25000000       0.00000000 </v>
   <v>      -0.25000000       0.25000000       0.00000000 </v>
   <v>       0.00000000       0.50000000       0.00000000 </v>
   <v>       0.25000000       0.50000000       0.00000000 </v>
   <v>       0.50000000       0.50000000       0.00000000 </v>
   <v>       0.00000000       0.00000000       0.25000000 </v>
   <v>       0.25000000       0.00000000       0.25000000 </v>
   <v>       0.50000000       0.00000000       0.25000000 </v>
   <v>      -0.25000000       0.00000000       0.25000000 </v>
   <v>       0.00000000       0.25000000       0.25000000 </v>
   <v>       0.25000000       0.25000000       0.25000000 </v>
   <v>       0.50000000       0.25000000       0.25000000 </v>
   <v>      -0.25000000       0.25000000       0.25000000 </v>
   <v>       0.00000000       0.50000000       0.25000000 </v>
   <v>       0.25000000       0.50000000       0.25000000 </v>
   <v>       0.50000000       0.50000000       0.25000000 </v>
   <v>      -0.25000000       0.50000000       0.25000000 </v>
   <v>       0.00000000      -0.25000000       0.25000000 </v>
   <v>       0.25000000      -0.25000000       0.25000000 </v>
   <v>       0.50000000      -0.25000000       0.25000000 </v>
   <v>      -0.25000000      -0.25000000       0.25000000 </v>
   <v>       0.00000000       0.00000000       0.50000000 </v>
   <v>       0.25000000       0.00000000       0.50000000 </v>
   <v>       0.50000000       0.00000000       0.50000000 </v>
   <v>       0.00000000       0.25000000       0.50000000 </v>
   <v>       0.25000000       0.25000000       0.50000000 </v>
   <v>       0.50000000       0.25000000       0.50000000 </v>
   <v>      -0.25000000       0.25000000       0.50000000 </v>
   <v>       0.00000000       0.50000000       0.50000000 </v>
   <v>       0.25000000       0.50000000       0.50000000 </v>
   <v>       0.50000000       0.50000000       0.50000000 </v>
  </varray>
  <varray name="weights" >
   <v>       0.01562500 </v>
   <v>       0.03125000 </v>
   <v>       0.01562500 </v>
   <v>       0.03125000 </v>
   <v>       0.03125000 </v>
   <v>       0.03125000 </v>
   <v>       0.03125000 </v>
   <v>       0.01562500 </v>
   <v>       0.03125000 </v>
   <v>       0.01562500 </v>
   <v>       0.03125000 </v>
   <v>       0.03125000 </v>
   <v>       0.03125000 </v>
   <v>       0.03125000 </v>
   <v>       0.03125000 </v>
   <v>       0.03125000 </v>
   <v>       0.03125000 </v>
   <v>       0.03125000 </v>
   <v>       0.03125000 </v>
   <v>       0.03125000 </v>
   <v>       0.03125000 </v>
   <v>       0.03125000 </v>
   <v>       0.03125000 </v>
   <v>       0.03125000 </v>
   <v>       0.03125000 </v>
   <v>       0.03125000 </v>
   <v>       0.01562500 </v>
   <v>       0.03125000 </v>
   <v>       0.01562500 </v>
   <v>       0.03125000 </v>
   <v>       0.03125000 </v>
   <v>       0.03125000 </v>
   <v>       0.03125000 </v>
   <v>       0.01562500 </v>
   <v>       0.03125000 </v>
   <v>       0.01562500 </v>
  </varray>
 </kpoints>
 <parameters>
  <separator name="general" >
   <i type="string" name="SYSTEM">unknown system</i>
   <i type="logical" name="LCOMPAT"> F  </i>
  </separator>
  <separator name="electronic" >
   <i type="string" name="PREC">accura</i>
   <i name="ENMAX">    600.00000000</i>
   <i name="ENAUG">    644.87300000</i>
   <i name="EDIFF">      0.00000100</i>
   <i type="int" name="IALGO">    68</i>
   <i type="int" name="IWAVPR">    11</i>
   <i type="int" name="NBANDS">    32</i>
   <i name="NELECT">     48.00000000</i>
   <i type="int" name="TURBO">     0</i>
   <i type="int" name="IRESTART">     0</i>
   <i type="int" name="NREBOOT">     0</i>
   <i type="int" name="NMIN">     0</i>
   <i name="EREF">      0.00000000</i>
   <separator name="electronic smearing" >
    <i type="int" name="ISMEAR">     0</i>
    <i name="SIGMA">      0.10000000</i>
    <i name="KSPACING">      0.50000000</i>
    <i type="logical" name="KGAMMA"> T  </i>
   </separator>
   <separator name="electronic projectors" >
    <i type="logical" name="LREAL"> F  </i>
    <v name="ROPT">      0.00000000      0.00000000      0.00000000      0.00000000</v>
    <i type="int" name="LMAXPAW">  -100</i>
    <i type="int" name="LMAXMIX">     2</i>
    <i type="logical" name="NLSPLINE"> F  </i>
   </separator>
   <separator name="electronic startup" >
    <i type="int" name="ISTART">     0</i>
    <i type="int" name="ICHARG">     2</i>
    <i type="int" name="INIWAV">     1</i>
   </separator>
   <separator name="electronic spin" >
    <i type="int" name="ISPIN">     1</i>
    <i type="logical" name="LNONCOLLINEAR"> F  </i>
    <v name="MAGMOM">      1.00000000      1.00000000      1.00000000      1.00000000      1.00000000      1.00000000      1.00000000      1.00000000      1.00000000      1.00000000      1.00000000      1.00000000</v>
    <i name="NUPDOWN">     -1.00000000</i>
    <i type="logical" name="LSORBIT"> F  </i>
    <v name="SAXIS">      0.00000000      0.00000000      1.00000000</v>
    <i type="logical" name="LSPIRAL"> F  </i>
    <v name="QSPIRAL">      0.00000000      0.00000000      0.00000000</v>
    <i type="logical" name="LZEROZ"> F  </i>
   </separator>
   <separator name="electronic exchange-correlation" >
    <i type="logical" name="LASPH"> F  </i>
    <i type="logical" name="LMETAGGA"> F  </i>
   </separator>
   <separator name="electronic convergence" >
    <i type="int" name="NELM">   100</i>
    <i type="int" name="NELMDL">     0</i>
    <i type="int" name="NELMIN">     4</i>
    <i name="ENINI">    600.00000000</i>
    <separator name="electronic convergence detail" >
     <i type="logical" name="LDIAG"> T  </i>
     <i type="logical" name="LSUBROT"> F  </i>
     <i name="WEIMIN">      0.00100000</i>
     <i name="EBREAK">      0.00000001</i>
     <i name="DEPER">      0.30000000</i>
     <i type="int" name="NRMM">     4</i>
     <i name="TIME">      0.40000000</i>
    </separator>
   </separator>
   <separator name="electronic mixer" >
    <i name="AMIX">      0.40000000</i>
    <i name="BMIX">      1.00000000</i>
    <i name="AMIN">      0.10000000</i>
    <i name="AMIX_MAG">      1.60000000</i>
    <i name="BMIX_MAG">      1.00000000</i>
    <separator name="electronic mixer details" >
     <i type="int" name="IMIX">     4</i>
     <i type="int" name="MAXMIX">   -45</i>
     <i name="WC">    100.00000000</i>
     <i type="int" name="INIMIX">     1</i>
     <i type="int" name="MIXPRE">     1</i>
     <i type="int" name="MREMOVE">     5</i>
    </separator>
   </separator>
   <separator name="electronic dipolcorrection" >
    <i type="logical" name="LDIPOL"> F  </i>
    <i type="logical" name="LMONO"> F  </i>
    <i type="int" name="IDIPOL">     0</i>
    <i name="EPSILON">      1.00000000</i>
    <v name="DIPOL">   -100.00000000   -100.00000000   -100.00000000</v>
    <i name="EFIELD">      0.00000000</i>
   </separator>
  </separator>
  <separator name="grids" >
   <i type="int" name="NGX">    48</i>
   <i type="int" name="NGY">    48</i>
   <i type="int" name="NGZ">    48</i>
   <i type="int" name="NGXF">    96</i>
   <i type="int" name="NGYF">    96</i>
   <i type="int" name="NGZF">    96</i>
   <i type="logical" name="ADDGRID"> T  </i>
  </separator>
  <separator name="ionic" >
   <i type="int" name="NSW">    30</i>
   <i type="int" name="IBRION">     2</i>
   <i type="int" name="ISIF">     3</i>
   <i name="PSTRESS">      0.00000000</i>
   <i name="EDIFFG">     -0.02000000</i>
   <i type="int" name="NFREE">     1</i>
   <i name="POTIM">      0.50000000</i>
   <i name="SMASS">     -3.00000000</i>
   <i name="SCALEE">      1.00000000</i>
  </separator>
  <separator name="ionic md" >
   <i name="TEBEG">      0.00010000</i>
   <i name="TEEND">      0.00010000</i>
   <i type="int" name="NBLOCK">     1</i>
   <i type="int" name="KBLOCK">    30</i>
   <i type="int" name="NPACO">   256</i>
   <i name="APACO">     16.00000000</i>
  </separator>
  <separator name="symmetry" >
   <i type="int" name="ISYM">     2</i>
   <i name="SYMPREC">      0.00001000</i>
  </separator>
  <separator name="dos" >
   <i type="logical" name="LORBIT"> F  </i>
   <v name="RWIGS">     -1.00000000     -1.00000000     -1.00000000     -1.00000000</v>
   <i type="int" name="NEDOS">   301</i>
   <i name="EMIN">     10.00000000</i>
   <i name="EMAX">    -10.00000000</i>
   <i name="EFERMI">      0.00000000</i>
  </separator>
  <separator name="writing" >
   <i type="int" name="NWRITE">     2</i>
   <i type="logical" name="LWAVE"> F  </i>
   <i type="logical" name="LCHARG"> F  </i>
   <i type="logical" name="LPARD"> F  </i>
   <i type="logical" name="LVTOT"> F  </i>
   <i type="logical" name="LVHAR"> F  </i>
   <i type="logical" name="LELF"> F  </i>
   <i type="logical" name="LOPTICS"> F  </i>
   <v name="STM">      0.00000000      0.00000000      0.00000000      0.00000000      0.00000000      0.00000000      0.00000000</v>
  </separator>
  <separator name="performance" >
   <i type="int" name="NPAR">     4</i>
   <i type="int" name="NSIM">     4</i>
   <i type="int" name="NBLK">    -1</i>
   <i type="logical" name="LPLANE"> T  </i>
   <i type="logical" name="LSCALAPACK"> T  </i>
   <i type="logical" name="LSCAAWARE"> F  </i>
   <i type="logical" name="LSCALU"> F  </i>
   <i type="logical" name="LASYNC"> F  </i>
   <i type="logical" name="LORBITALREAL"> F  </i>
  </separator>
  <separator name="miscellaneous" >
   <i type="int" name="IDIOT">     3</i>
   <i type="logical" name="LMUSIC"> F  </i>
   <v name="POMASS">     28.08500000     26.98100000     12.01100000     14.00100000</v>
   <v name="DARWINR">      0.00000000      0.00000000      0.00000000      0.00000000</v>
   <v name="DARWINV">      1.00000000      1.00000000      1.00000000      1.00000000</v>
   <i type="logical" name="LCORR"> T  </i>
  </separator>
  <i type="logical" name="GGA_COMPAT"> T  </i>
  <i type="logical" name="LBERRY"> F  </i>
  <i type="int" name="ICORELEVEL">     0</i>
  <i type="logical" name="LDAU"> F  </i>
  <i type="int" name="I_CONSTRAINED_M">     0</i>
  <separator name="electronic exchange-correlation" >
   <i type="string" name="GGA">--</i>
   <i type="int" name="VOSKOWN">     0</i>
   <i type="logical" name="LHFCALC"> F  </i>
   <i type="string" name="PRECFOCK"></i>
   <i type="logical" name="LSYMGRAD"> F  </i>
   <i type="logical" name="LHFONE"> F  </i>
   <i type="logical" name="LRHFCALC"> F  </i>
   <i type="logical" name="LTHOMAS"> F  </i>
   <i type="logical" name="LMODELHF"> F  </i>
   <i name="ENCUT4O">     -1.00000000</i>
   <i type="int" name="EXXOEP">     0</i>
   <i type="int" name="FOURORBIT">     0</i>
   <i name="AEXX">      0.00000000</i>
   <i name="HFALPHA">      0.00000000</i>
   <i name="MCALPHA">      0.00000000</i>
   <i name="ALDAX">      1.00000000</i>
   <i name="AGGAX">      1.00000000</i>
   <i name="ALDAC">      1.00000000</i>
   <i name="AGGAC">      1.00000000</i>
   <i type="int" name="NKREDX">     1</i>
   <i type="int" name="NKREDY">     1</i>
   <i type="int" name="NKREDZ">     1</i>
   <i type="logical" name="SHIFTRED"> F  </i>
   <i type="logical" name="ODDONLY"> F  </i>
   <i type="logical" name="EVENONLY"> F  </i>
   <i type="int" name="LMAXFOCK">     0</i>
   <i type="int" name="NMAXFOCKAE">     0</i>
   <i type="logical" name="LFOCKAEDFT"> F  </i>
   <i name="HFSCREEN">      0.00000000</i>
   <i name="HFSCREENC">      0.00000000</i>
   <i type="int" name="NBANDSGWLOW">     0</i>
  </separator>
  <separator name="vdW DFT" >
   <i type="logical" name="LUSE_VDW"> F  </i>
   <i name="Zab_VDW">     -0.84910000</i>
   <i name="PARAM1">      0.12340000</i>
   <i name="PARAM2">      1.00000000</i>
   <i name="PARAM3">      0.00000000</i>
  </separator>
  <separator name="model GW" >
   <i type="int" name="MODEL_GW">     0</i>
   <i name="MODEL_EPS0">      6.38126941</i>
   <i name="MODEL_ALPHA">      1.00000000</i>
  </separator>
  <separator name="linear response parameters" >
   <i type="logical" name="LEPSILON"> F  </i>
   <i type="logical" name="LRPA"> F  </i>
   <i type="logical" name="LNABLA"> F  </i>
   <i type="logical" name="LVEL"> F  </i>
   <i type="int" name="KINTER">     0</i>
   <i name="CSHIFT">      0.10000000</i>
   <i name="OMEGAMAX">     -1.00000000</i>
   <i name="DEG_THRESHOLD">      0.00200000</i>
  </separator>
  <separator name="orbital magnetization" >
   <i type="logical" name="NUCIND"> F  </i>
   <v name="MAGPOS">      0.00000000      0.00000000      0.00000000</v>
   <i type="logical" name="LNICSALL"> T  </i>
   <i type="logical" name="ORBITALMAG"> F  </i>
   <i type="logical" name="LMAGBLOCH"> F  </i>
   <i type="logical" name="LCHIMAG"> F  </i>
   <i type="logical" name="LGAUGE"> T  </i>
   <i type="int" name="MAGATOM">     0</i>
   <v name="MAGDIPOL">      0.00000000      0.00000000      0.00000000</v>
   <v name="AVECCONST">      0.00000000      0.00000000      0.00000000</v>
  </separator>
  <separator name="response functions" >
   <i type="logical" name="LADDER"> F  </i>
   <i type="logical" name="LFXC"> F  </i>
   <i type="logical" name="LHARTREE"> T  </i>
   <i type="int" name="IBSE">     0</i>
   <i type="logical" name="LTCTE"> F  </i>
   <i type="logical" name="LTETE"> F  </i>
   <i type="logical" name="LTRIPLET"> F  </i>
   <i type="logical" name="LFXCEPS"> F  </i>
   <i type="logical" name="LFXHEG"> F  </i>
   <i type="logical" name="L2ORDER"> F  </i>
   <i type="logical" name="LUSEW"> F  </i>
   <i name="ENCUTGW">     -2.00000000</i>
   <i name="ENCUTGWSOFT">     -2.00000000</i>
   <i name="ENCUTLF">     -1.00000000</i>
   <i type="int" name="LMAXMP2">    -1</i>
   <i name="SCISSOR">      0.00000000</i>
   <i type="int" name="NOMEGA">     0</i>
   <i type="int" name="NOMEGAR">     0</i>
   <i type="int" name="NBANDSGW">    -1</i>
   <i type="int" name="NBANDSO">    -1</i>
   <i type="int" name="NBANDSV">    -1</i>
   <i type="int" name="NELM">   100</i>
   <i type="int" name="DIM">     3</i>
   <i type="int" name="ANTIRES">     0</i>
   <i name="OMEGAMAX">    -30.00000000</i>
   <i name="OMEGAMIN">    -30.00000000</i>
   <i name="OMEGATL">   -200.00000000</i>
   <i type="int" name="OMEGAGRID">     0</i>
   <i name="CSHIFT">     -0.10000000</i>
   <i type="logical" name="SELFENERGY"> F  </i>
   <i type="logical" name="LSPECTRAL"> F  </i>
   <i type="logical" name="ODDONLYGW"> F  </i>
   <i type="logical" name="EVENONLYGW"> F  </i>
   <i type="int" name="NKREDLFX">     1</i>
   <i type="int" name="NKREDLFY">     1</i>
   <i type="int" name="NKREDLFZ">     1</i>
   <i type="int" name="MAXMEM">  1800</i>
   <i type="int" name="TELESCOPE">     0</i>
   <i type="int" name="TAUPAR">     1</i>
  </separator>
  <separator name="External order field" >
   <i name="OFIELD_KAPPA">      0.00000000</i>
   <v name="OFIELD_K">      0.00000000      0.00000000      0.00000000</v>
   <i name="OFIELD_Q6_NEAR">      0.00000000</i>
   <i name="OFIELD_Q6_FAR">      0.00000000</i>
   <i name="OFIELD_A">      0.00000000</i>
  </separator>
 </parameters>
 <atominfo>
  <atoms>      12 </atoms>
  <types>       4 </types>
  <array name="atoms" >
   <dimension dim="1">ion</dimension>
   <field type="string">element</field>
   <field type="int">atomtype</field>
   <set>
    <rc><c>Si</c><c>   1</c></rc>
    <rc><c>Si</c><c>   1</c></rc>
    <rc><c>Si</c><c>   1</c></rc>
    <rc><c>Al</c><c>   2</c></rc>
    <rc><c>Al</c><c>   2</c></rc>
    <rc><c>Al</c><c>   2</c></rc>
    <rc><c>C </c><c>   3</c></rc>
    <rc><c>C </c><c>   3</c></rc>
    <rc><c>C </c><c>   3</c></rc>
    <rc><c>N </c><c>   4</c></rc>
    <rc><c>N </c><c>   4</c></rc>
    <rc><c>N </c><c>   4</c></rc>
   </set>
  </array>
  <array name="atomtypes" >
   <dimension dim="1">type</dimension>
   <field type="int">atomspertype</field>
   <field type="string">element</field>
   <field>mass</field>
   <field>valence</field>
   <field type="string">pseudopotential</field>
   <set>
    <rc><c>   3</c><c>Si</c><c>     28.08500000</c><c>      4.00000000</c><c>  PAW_PBE Si 05Jan2001                  </c></rc>
    <rc><c>   3</c><c>Al</c><c>     26.98100000</c><c>      3.00000000</c><c>  PAW_PBE Al 04Jan2001                  </c></rc>
    <rc><c>   3</c><c>C </c><c>     12.01100000</c><c>      4.00000000</c><c>  PAW_PBE C 08Apr2002                   </c></rc>
    <rc><c>   3</c><c>N </c><c>     14.00100000</c><c>      5.00000000</c><c>  PAW_PBE N_s 07Sep2000                 </c></rc>
   </set>
  </array>
 </atominfo>
 <structure name="initialpos" >
  <crystal>
   <varray name="basis" >
    <v>       5.40345231       0.01419918      -0.01828798 </v>
    <v>       2.71397382       4.68842978      -0.02388673 </v>
    <v>       2.68860528       1.55157548       5.03149486 </v>
   </varray>
   <i name="volume">    127.62538828 </i>
   <varray name="rec_basis" >
    <v>       0.18512674      -0.10749873      -0.06577376 </v>
    <v>      -0.00078212       0.21341061      -0.06539207 </v>
    <v>       0.00066917       0.00062243       0.19819858 </v>
   </varray>
  </crystal>
  <varray name="positions" >
   <v>       0.00322141       0.67357921       0.98998684 </v>
   <v>       0.49074790       0.83536698       0.50731941 </v>
   <v>       0.16838619       0.49915622       0.50846631 </v>
   <v>       0.66339513       0.33161658       0.00020724 </v>
   <v>       0.34407688       0.00214996       0.98380360 </v>
   <v>       0.83733282       0.16245101       0.49909292 </v>
   <v>       0.51817808       0.20146250       0.39084581 </v>
   <v>       0.36203311       0.70700742       0.86747040 </v>
   <v>       0.03569535       0.39565514       0.87420963 </v>
   <v>       0.22635770       0.85457648       0.37743993 </v>
   <v>       0.87423869       0.56344319       0.37045732 </v>
   <v>       0.72633673       0.02353529       0.88070057 </v>
  </varray>
 </structure>
 <calculation>
  <scstep>
   <time name="dav">    0.67    0.67</time>
   <time name="total">    0.74    0.75</time>
   <energy>
    <i name="alphaZ">     47.93783767 </i>
    <i name="ewald">  -1706.36854006 </i>
    <i name="hartreedc">   -266.66411839 </i>
    <i name="XCdc">     -4.08875642 </i>
    <i name="pawpsdc">   1403.35320608 </i>
    <i name="pawaedc">  -1259.97391932 </i>
    <i name="eentropy">     -0.00927753 </i>
    <i name="bandstr">    333.41327901 </i>
    <i name="atom">   1704.90733868 </i>
    <i name="e_fr_energy">    252.50704971 </i>
    <i name="e_wo_entrp">    252.51632725 </i>
    <i name="e_0_energy">    252.51168848 </i>
   </energy>
  </scstep>
  <scstep>
   <time name="dav">    0.79    0.79</time>
   <time name="total">    0.79    0.81</time>
   <energy>
    <i name="e_fr_energy">    -79.08968243 </i>
    <i name="e_wo_entrp">    -79.08968243 </i>
    <i name="e_0_energy">    -79.08968243 </i>
   </energy>
  </scstep>
  <scstep>
   <time name="dav">    0.82    0.82</time>
   <time name="total">    0.82    0.83</time>
   <energy>
    <i name="e_fr_energy">   -100.74523974 </i>
    <i name="e_wo_entrp">   -100.74523974 </i>
    <i name="e_0_energy">   -100.74523974 </i>
   </energy>
  </scstep>
  <scstep>
   <time name="dav">    0.80    0.80</time>
   <time name="total">    0.80    0.81</time>
   <energy>
    <i name="e_fr_energy">   -101.27569199 </i>
    <i name="e_wo_entrp">   -101.27569199 </i>
    <i name="e_0_energy">   -101.27569199 </i>
   </energy>
  </scstep>
  <scstep>
   <time name="dav">    0.78    0.78</time>
   <time name="total">    0.88    0.90</time>
   <energy>
    <i name="e_fr_energy">   -101.29323616 </i>
    <i name="e_wo_entrp">   -101.29323616 </i>
    <i name="e_0_energy">   -101.29323616 </i>
   </energy>
  </scstep>
  <scstep>
   <time name="diag">    0.16    0.16</time>
   <time name="diis">    0.48    0.48</time>
   <time name="orth">    0.02    0.02</time>
   <time name="total">    0.84    0.85</time>
   <energy>
    <i name="e_fr_energy">    -88.00299673 </i>
    <i name="e_wo_entrp">    -88.00299673 </i>
    <i name="e_0_energy">    -88.00299673 </i>
   </energy>
  </scstep>
  <scstep>
   <time name="diag">    0.16    0.16</time>
   <time name="diis">    0.53    0.53</time>
   <time name="orth">    0.03    0.03</time>
   <time name="total">    0.89    0.91</time>
   <energy>
    <i name="e_fr_energy">    -87.97284513 </i>
    <i name="e_wo_entrp">    -87.97284513 </i>
    <i name="e_0_energy">    -87.97284513 </i>
   </energy>
  </scstep>
  <scstep>
   <time name="diag">    0.16    0.16</time>
   <time name="diis">    0.49    0.49</time>
   <time name="orth">    0.02    0.02</time>
   <time name="total">    0.85    0.86</time>
   <energy>
    <i name="e_fr_energy">    -88.10011325 </i>
    <i name="e_wo_entrp">    -88.10011325 </i>
    <i name="e_0_energy">    -88.10011325 </i>
   </energy>
  </scstep>
  <scstep>
   <time name="diag">    0.16    0.16</time>
   <time name="diis">    0.49    0.49</time>
   <time name="orth">    0.02    0.02</time>
   <time name="total">    0.84    0.85</time>
   <energy>
    <i name="e_fr_energy">    -87.87625043 </i>
    <i name="e_wo_entrp">    -87.87625043 </i>
    <i name="e_0_energy">    -87.87625043 </i>
   </energy>
  </scstep>
  <scstep>
   <time name="diag">    0.16    0.16</time>
   <time name="diis">    0.50    0.50</time>
   <time name="orth">    0.02    0.02</time>
   <time name="total">    0.86    0.87</time>
   <energy>
    <i name="e_fr_energy">    -87.87983465 </i>
    <i name="e_wo_entrp">    -87.87983465 </i>
    <i name="e_0_energy">    -87.87983465 </i>
   </energy>
  </scstep>
  <scstep>
   <time name="diag">    0.16    0.16</time>
   <time name="diis">    0.49    0.49</time>
   <time name="orth">    0.02    0.02</time>
   <time name="total">    0.84    0.85</time>
   <energy>
    <i name="e_fr_energy">    -87.87914041 </i>
    <i name="e_wo_entrp">    -87.87914041 </i>
    <i name="e_0_energy">    -87.87914041 </i>
   </energy>
  </scstep>
  <scstep>
   <time name="diag">    0.16    0.16</time>
   <time name="diis">    0.48    0.48</time>
   <time name="orth">    0.02    0.02</time>
   <time name="total">    0.83    0.85</time>
   <energy>
    <i name="e_fr_energy">    -87.87873833 </i>
    <i name="e_wo_entrp">    -87.87873833 </i>
    <i name="e_0_energy">    -87.87873833 </i>
   </energy>
  </scstep>
  <scstep>
   <time name="diag">    0.16    0.16</time>
   <time name="diis">    0.49    0.49</time>
   <time name="orth">    0.02    0.02</time>
   <time name="total">    0.84    0.85</time>
   <energy>
    <i name="e_fr_energy">    -87.87874631 </i>
    <i name="e_wo_entrp">    -87.87874631 </i>
    <i name="e_0_energy">    -87.87874631 </i>
   </energy>
  </scstep>
  <scstep>
   <time name="diag">    0.16    0.16</time>
   <time name="diis">    0.47    0.47</time>
   <time name="orth">    0.02    0.02</time>
   <time name="total">    0.83    0.84</time>
   <energy>
    <i name="e_fr_energy">    -87.87874897 </i>
    <i name="e_wo_entrp">    -87.87874897 </i>
    <i name="e_0_energy">    -87.87874897 </i>
   </energy>
  </scstep>
  <scstep>
   <time name="diag">    0.16    0.16</time>
   <time name="diis">    0.32    0.32</time>
   <time name="orth">    0.02    0.02</time>
   <time name="total">    0.57    0.59</time>
   <energy>
    <i name="alphaZ">     47.93783767 </i>
    <i name="ewald">  -1706.36854006 </i>
    <i name="hartreedc">   -348.31686693 </i>
    <i name="XCdc">      3.12556711 </i>
    <i name="pawpsdc">   7654.52150868 </i>
    <i name="pawaedc">  -7514.28296357 </i>
    <i name="eentropy">      0.00000000 </i>
    <i name="bandstr">     70.59736916 </i>
    <i name="atom">   1704.90733868 </i>
    <i name="e_fr_energy">    -87.87874928 </i>
    <i name="e_wo_entrp">    -87.87874928 </i>
    <i name="e_0_energy">    -87.87874928 </i>
   </energy>
  </scstep>
  <structure>
   <crystal>
    <varray name="basis" >
     <v>       5.40345231       0.01419918      -0.01828798 </v>
     <v>       2.71397382       4.68842978      -0.02388673 </v>
     <v>       2.68860528       1.55157548       5.03149486 </v>
    </varray>
    <i name="volume">    127.62538828 </i>
    <varray name="rec_basis" >
     <v>       0.18512674      -0.10749873      -0.06577376 </v>
     <v>      -0.00078212       0.21341061      -0.06539207 </v>
     <v>       0.00066917       0.00062243       0.19819858 </v>
    </varray>
   </crystal>
   <varray name="positions" >
    <v>       0.00322141       0.67357921       0.98998684 </v>
    <v>       0.49074790       0.83536698       0.50731941 </v>
    <v>       0.16838619       0.49915622       0.50846631 </v>
    <v>       0.66339513       0.33161658       0.00020724 </v>
    <v>       0.34407688       0.00214996       0.98380360 </v>
    <v>       0.83733282       0.16245101       0.49909292 </v>
    <v>       0.51817808       0.20146250       0.39084581 </v>
    <v>       0.36203311       0.70700742       0.86747040 </v>
    <v>       0.03569535       0.39565514       0.87420963 </v>
    <v>       0.22635770       0.85457648       0.37743993 </v>
    <v>       0.87423869       0.56344319       0.37045732 </v>
    <v>       0.72633673       0.02353529       0.88070057 </v>
   </varray>
  </structure>
  <varray name="forces" >
   <v>      -0.00708847      -0.00276813      -0.01063800 </v>
   <v>      -0.00242084       0.00132445       0.01541380 </v>
   <v>      -0.00365451      -0.00034646       0.00677123 </v>
   <v>      -0.00005184      -0.00506120      -0.00075135 </v>
   <v>       0.01023211      -0.00038464       0.00012857 </v>
   <v>      -0.00461157       0.00364784      -0.00210002 </v>
   <v>       0.00245437      -0.00278749      -0.00239423 </v>
   <v>      -0.00175778       0.00215605       0.00498510 </v>
   <v>       0.00030575       0.00086186      -0.00071664 </v>
   <v>       0.00398225      -0.00186538      -0.00413799 </v>
   <v>      -0.00093941       0.00163775      -0.00443771 </v>
   <v>       0.00354994       0.00358535      -0.00212275 </v>
  </varray>
  <varray name="stress" >
   <v>       0.01391840      -0.04476080      -0.01929822 </v>
   <v>      -0.04476056       0.15917450       0.04732557 </v>
   <v>      -0.01929862       0.04732532      -0.25995756 </v>
  </varray>
  <energy>
   <i name="e_fr_energy">    -87.87874928 </i>
   <i name="e_wo_entrp">    -87.87874928 </i>
   <i name="e_0_energy">      0.00000000 </i>
  </energy>
  <time name="totalsc">   14.11   14.34</time>
  <eigenvalues>
   <array>
    <dimension dim="1">band</dimension>
    <dimension dim="2">kpoint</dimension>
    <dimension dim="3">spin</dimension>
    <field>eigene</field>
    <field>occ</field>
    <set>
     <set comment="spin 1">
      <set comment="kpoint 1">
       <r>   -9.1232    1.0000 </r>
       <r>   -7.2208    1.0000 </r>
       <r>   -7.0329    1.0000 </r>
       <r>   -3.9940    1.0000 </r>
       <r>   -2.8949    1.0000 </r>
       <r>   -2.5399    1.0000 </r>
       <r>   -0.5237    1.0000 </r>
       <r>   -0.3201    1.0000 </r>
       <r>    0.8617    1.0000 </r>
       <r>    1.2040    1.0000 </r>
       <r>    1.6078    1.0000 </r>
       <r>    1.8425    1.0000 </r>
       <r>    2.5205    1.0000 </r>
       <r>    3.1924    1.0000 </r>
       <r>    3.3498    1.0000 </r>
       <r>    4.5089    1.0000 </r>
       <r>    4.9682    1.0000 </r>
       <r>    5.3372    1.0000 </r>
       <r>    5.6769    1.0000 </r>
       <r>    5.9825    1.0000 </r>
       <r>    6.2685    1.0000 </r>
       <r>    7.2966    1.0000 </r>
       <r>    7.4275    1.0000 </r>
       <r>    7.6561    1.0000 </r>
       <r>   11.0123    0.0000 </r>
       <r>   12.2311    0.0000 </r>
       <r>   12.3744    0.0000 </r>
       <r>   12.6698    0.0000 </r>
       <r>   13.1437    0.0000 </r>
       <r>   13.8997    0.0000 </r>
       <r>   14.4286    0.0000 </r>
       <r>   14.6732    0.0000 </r>
      </set>
      <set comment="kpoint 2">
       <r>   -8.8798    1.0000 </r>
       <r>   -7.5011    1.0000 </r>
       <r>   -7.0405    1.0000 </r>
       <r>   -4.2533    1.0000 </r>
       <r>   -3.0326    1.0000 </r>
       <r>   -2.7178    1.0000 </r>
       <r>   -0.3829    1.0000 </r>
       <r>   -0.0715    1.0000 </r>
       <r>    0.6633    1.0000 </r>
       <r>    1.2492    1.0000 </r>
       <r>    1.8953    1.0000 </r>
       <r>    2.4203    1.0000 </r>
       <r>    3.2014    1.0000 </r>
       <r>    3.5181    1.0000 </r>
       <r>    4.0014    1.0000 </r>
       <r>    4.2715    1.0000 </r>
       <r>    4.6497    1.0000 </r>
       <r>    5.1236    1.0000 </r>
       <r>    5.4897    1.0000 </r>
       <r>    5.6807    1.0000 </r>
       <r>    6.0675    1.0000 </r>
       <r>    6.6027    1.0000 </r>
       <r>    7.1704    1.0000 </r>
       <r>    7.4971    1.0000 </r>
       <r>   11.5593    0.0000 </r>
       <r>   12.0242    0.0000 </r>
       <r>   12.1673    0.0000 </r>
       <r>   12.7750    0.0000 </r>
       <r>   13.4211    0.0000 </r>
       <r>   13.7826    0.0000 </r>
       <r>   14.4267    0.0000 </r>
       <r>   14.5597    0.0000 </r>
      </set>
      <set comment="kpoint 3">
       <r>   -8.4038    1.0000 </r>
       <r>   -8.0159    1.0000 </r>
       <r>   -7.0481    1.0000 </r>
       <r>   -4.5007    1.0000 </r>
       <r>   -3.1507    1.0000 </r>
       <r>   -2.8664    1.0000 </r>
       <r>   -0.4563    1.0000 </r>
       <r>    0.2857    1.0000 </r>
       <r>    1.0665    1.0000 </r>
       <r>    1.6135    1.0000 </r>
       <r>    1.9814    1.0000 </r>
       <r>    2.7067    1.0000 </r>
       <r>    3.0396    1.0000 </r>
       <r>    3.8686    1.0000 </r>
       <r>    4.0553    1.0000 </r>
       <r>    4.0904    1.0000 </r>
       <r>    4.7570    1.0000 </r>
       <r>    4.9519    1.0000 </r>
       <r>    5.4310    1.0000 </r>
       <r>    5.9857    1.0000 </r>
       <r>    6.0497    1.0000 </r>
       <r>    6.4269    1.0000 </r>
       <r>    6.7034    1.0000 </r>
       <r>    7.3875    1.0000 </r>
       <r>   10.6828    0.0000 </r>
       <r>   11.7565    0.0000 </r>
       <r>   12.6192    0.0000 </r>
       <r>   13.0206    0.0000 </r>
       <r>   13.3625    0.0000 </r>
       <r>   13.5493    0.0000 </r>
       <r>   14.0089    0.0000 </r>
       <r>   14.4832    0.0000 </r>
      </set>
      <set comment="kpoint 4">
       <r>   -8.9271    1.0000 </r>
       <r>   -7.3646    1.0000 </r>
       <r>   -7.0808    1.0000 </r>
       <r>   -4.2213    1.0000 </r>
       <r>   -3.4270    1.0000 </r>
       <r>   -2.3614    1.0000 </r>
       <r>   -0.5649    1.0000 </r>
       <r>   -0.1870    1.0000 </r>
       <r>    1.0423    1.0000 </r>
       <r>    1.1242    1.0000 </r>
       <r>    1.9214    1.0000 </r>
       <r>    2.6117    1.0000 </r>
       <r>    2.8270    1.0000 </r>
       <r>    3.6308    1.0000 </r>
       <r>    4.1713    1.0000 </r>
       <r>    4.3338    1.0000 </r>
       <r>    4.7265    1.0000 </r>
       <r>    4.9395    1.0000 </r>
       <r>    5.3996    1.0000 </r>
       <r>    5.8157    1.0000 </r>
       <r>    5.9801    1.0000 </r>
       <r>    6.6591    1.0000 </r>
       <r>    7.1501    1.0000 </r>
       <r>    7.4709    1.0000 </r>
       <r>   11.4599    0.0000 </r>
       <r>   11.9821    0.0000 </r>
       <r>   12.1235    0.0000 </r>
       <r>   12.7914    0.0000 </r>
       <r>   13.4888    0.0000 </r>
       <r>   13.8115    0.0000 </r>
       <r>   13.9549    0.0000 </r>
       <r>   14.6615    0.0000 </r>
      </set>
      <set comment="kpoint 5">
       <r>   -8.8392    1.0000 </r>
       <r>   -7.4724    1.0000 </r>
       <r>   -7.1407    1.0000 </r>
       <r>   -4.0675    1.0000 </r>
       <r>   -3.4709    1.0000 </r>
       <r>   -2.7054    1.0000 </r>
       <r>   -0.2914    1.0000 </r>
       <r>    0.2159    1.0000 </r>
       <r>    0.8352    1.0000 </r>
       <r>    1.4162    1.0000 </r>
       <r>    2.0315    1.0000 </r>
       <r>    2.6012    1.0000 </r>
       <r>    2.8473    1.0000 </r>
       <r>    3.5260    1.0000 </r>
       <r>    3.8698    1.0000 </r>
       <r>    4.2082    1.0000 </r>
       <r>    4.5575    1.0000 </r>
       <r>    5.1341    1.0000 </r>
       <r>    5.3557    1.0000 </r>
       <r>    5.6649    1.0000 </r>
       <r>    6.0282    1.0000 </r>
       <r>    6.5962    1.0000 </r>
       <r>    7.0016    1.0000 </r>
       <r>    7.3541    1.0000 </r>
       <r>   11.4321    0.0000 </r>
       <r>   11.9889    0.0000 </r>
       <r>   12.4407    0.0000 </r>
       <r>   12.8139    0.0000 </r>
       <r>   13.2449    0.0000 </r>
       <r>   13.8754    0.0000 </r>
       <r>   14.2491    0.0000 </r>
       <r>   14.6835    0.0000 </r>
      </set>
      <set comment="kpoint 6">
       <r>   -8.3794    1.0000 </r>
       <r>   -7.9429    1.0000 </r>
       <r>   -7.1674    1.0000 </r>
       <r>   -4.4236    1.0000 </r>
       <r>   -3.3267    1.0000 </r>
       <r>   -3.0927    1.0000 </r>
       <r>   -0.0775    1.0000 </r>
       <r>    0.7617    1.0000 </r>
       <r>    1.0974    1.0000 </r>
       <r>    1.7041    1.0000 </r>
       <r>    2.2259    1.0000 </r>
       <r>    2.4484    1.0000 </r>
       <r>    2.8797    1.0000 </r>
       <r>    3.4670    1.0000 </r>
       <r>    3.9378    1.0000 </r>
       <r>    4.2906    1.0000 </r>
       <r>    4.6927    1.0000 </r>
       <r>    4.9307    1.0000 </r>
       <r>    5.4924    1.0000 </r>
       <r>    5.7447    1.0000 </r>
       <r>    5.9252    1.0000 </r>
       <r>    6.3188    1.0000 </r>
       <r>    6.9075    1.0000 </r>
       <r>    7.2832    1.0000 </r>
       <r>   11.2614    0.0000 </r>
       <r>   11.5228    0.0000 </r>
       <r>   12.1698    0.0000 </r>
       <r>   12.2999    0.0000 </r>
       <r>   12.5735    0.0000 </r>
       <r>   13.6382    0.0000 </r>
       <r>   14.2255    0.0000 </r>
       <r>   14.9665    0.0000 </r>
      </set>
      <set comment="kpoint 7">
       <r>   -8.5987    1.0000 </r>
       <r>   -7.6761    1.0000 </r>
       <r>   -7.1388    1.0000 </r>
       <r>   -4.5034    1.0000 </r>
       <r>   -3.4009    1.0000 </r>
       <r>   -2.8089    1.0000 </r>
       <r>   -0.2430    1.0000 </r>
       <r>    0.3194    1.0000 </r>
       <r>    0.9265    1.0000 </r>
       <r>    1.6970    1.0000 </r>
       <r>    2.1303    1.0000 </r>
       <r>    2.4541    1.0000 </r>
       <r>    3.3775    1.0000 </r>
       <r>    3.7196    1.0000 </r>
       <r>    3.7774    1.0000 </r>
       <r>    4.3689    1.0000 </r>
       <r>    4.5634    1.0000 </r>
       <r>    5.0721    1.0000 </r>
       <r>    5.5062    1.0000 </r>
       <r>    5.7123    1.0000 </r>
       <r>    6.0176    1.0000 </r>
       <r>    6.3374    1.0000 </r>
       <r>    6.9696    1.0000 </r>
       <r>    7.4859    1.0000 </r>
       <r>   11.0496    0.0000 </r>
       <r>   11.3757    0.0000 </r>
       <r>   12.0809    0.0000 </r>
       <r>   12.5976    0.0000 </r>
       <r>   12.9915    0.0000 </r>
       <r>   13.5842    0.0000 </r>
       <r>   14.0834    0.0000 </r>
       <r>   14.3576    0.0000 </r>
      </set>
      <set comment="kpoint 8">
       <r>   -8.6529    1.0000 </r>
       <r>   -7.6069    1.0000 </r>
       <r>   -7.1127    1.0000 </r>
       <r>   -4.4755    1.0000 </r>
       <r>   -3.6976    1.0000 </r>
       <r>   -2.4014    1.0000 </r>
       <r>   -0.4570    1.0000 </r>
       <r>   -0.1435    1.0000 </r>
       <r>    1.1231    1.0000 </r>
       <r>    1.7079    1.0000 </r>
       <r>    2.5245    1.0000 </r>
       <r>    2.7200    1.0000 </r>
       <r>    2.8556    1.0000 </r>
       <r>    3.7064    1.0000 </r>
       <r>    4.2265    1.0000 </r>
       <r>    4.4427    1.0000 </r>
       <r>    4.7016    1.0000 </r>
       <r>    4.8193    1.0000 </r>
       <r>    5.3512    1.0000 </r>
       <r>    5.7501    1.0000 </r>
       <r>    6.1082    1.0000 </r>
       <r>    6.5034    1.0000 </r>
       <r>    6.8442    1.0000 </r>
       <r>    7.1426    1.0000 </r>
       <r>   10.7120    0.0000 </r>
       <r>   11.6257    0.0000 </r>
       <r>   12.7326    0.0000 </r>
       <r>   12.8085    0.0000 </r>
       <r>   13.3000    0.0000 </r>
       <r>   13.5168    0.0000 </r>
       <r>   13.8941    0.0000 </r>
       <r>   14.1380    0.0000 </r>
      </set>
      <set comment="kpoint 9">
       <r>   -8.5342    1.0000 </r>
       <r>   -7.6826    1.0000 </r>
       <r>   -7.2254    1.0000 </r>
       <r>   -4.3846    1.0000 </r>
       <r>   -3.7163    1.0000 </r>
       <r>   -2.7825    1.0000 </r>
       <r>   -0.0586    1.0000 </r>
       <r>    0.3742    1.0000 </r>
       <r>    1.3318    1.0000 </r>
       <r>    1.7748    1.0000 </r>
       <r>    2.2543    1.0000 </r>
       <r>    2.5385    1.0000 </r>
       <r>    2.9011    1.0000 </r>
       <r>    3.6489    1.0000 </r>
       <r>    3.9126    1.0000 </r>
       <r>    4.2311    1.0000 </r>
       <r>    4.5939    1.0000 </r>
       <r>    4.8369    1.0000 </r>
       <r>    5.5204    1.0000 </r>
       <r>    5.7245    1.0000 </r>
       <r>    6.0148    1.0000 </r>
       <r>    6.3877    1.0000 </r>
       <r>    6.7629    1.0000 </r>
       <r>    7.3237    1.0000 </r>
       <r>   11.0285    0.0000 </r>
       <r>   11.4928    0.0000 </r>
       <r>   12.0353    0.0000 </r>
       <r>   12.5635    0.0000 </r>
       <r>   12.9860    0.0000 </r>
       <r>   13.5003    0.0000 </r>
       <r>   13.9319    0.0000 </r>
       <r>   14.5558    0.0000 </r>
      </set>
      <set comment="kpoint 10">
       <r>   -8.2766    1.0000 </r>
       <r>   -7.9873    1.0000 </r>
       <r>   -7.2524    1.0000 </r>
       <r>   -4.2093    1.0000 </r>
       <r>   -3.5881    1.0000 </r>
       <r>   -3.2971    1.0000 </r>
       <r>   -0.0027    1.0000 </r>
       <r>    1.0147    1.0000 </r>
       <r>    1.4149    1.0000 </r>
       <r>    1.8044    1.0000 </r>
       <r>    2.4793    1.0000 </r>
       <r>    2.5566    1.0000 </r>
       <r>    3.2609    1.0000 </r>
       <r>    3.6124    1.0000 </r>
       <r>    3.6960    1.0000 </r>
       <r>    3.9992    1.0000 </r>
       <r>    4.4783    1.0000 </r>
       <r>    4.5167    1.0000 </r>
       <r>    5.2033    1.0000 </r>
       <r>    5.6663    1.0000 </r>
       <r>    5.9017    1.0000 </r>
       <r>    6.0879    1.0000 </r>
       <r>    6.7275    1.0000 </r>
       <r>    7.1915    1.0000 </r>
       <r>   10.9581    0.0000 </r>
       <r>   11.9548    0.0000 </r>
       <r>   12.2479    0.0000 </r>
       <r>   12.8246    0.0000 </r>
       <r>   13.1781    0.0000 </r>
       <r>   13.8984    0.0000 </r>
       <r>   14.0317    0.0000 </r>
       <r>   14.6703    0.0000 </r>
      </set>
      <set comment="kpoint 11">
       <r>   -8.9693    1.0000 </r>
       <r>   -7.3856    1.0000 </r>
       <r>   -7.1102    1.0000 </r>
       <r>   -4.1351    1.0000 </r>
       <r>   -3.1180    1.0000 </r>
       <r>   -2.6544    1.0000 </r>
       <r>   -0.1054    1.0000 </r>
       <r>    0.2987    1.0000 </r>
       <r>    1.1312    1.0000 </r>
       <r>    1.3528    1.0000 </r>
       <r>    1.5583    1.0000 </r>
       <r>    2.0447    1.0000 </r>
       <r>    2.7411    1.0000 </r>
       <r>    3.3843    1.0000 </r>
       <r>    3.6155    1.0000 </r>
       <r>    3.9607    1.0000 </r>
       <r>    4.2136    1.0000 </r>
       <r>    5.2356    1.0000 </r>
       <r>    5.4367    1.0000 </r>
       <r>    5.8151    1.0000 </r>
       <r>    6.1323    1.0000 </r>
       <r>    6.7051    1.0000 </r>
       <r>    7.3561    1.0000 </r>
       <r>    7.5404    1.0000 </r>
       <r>   10.8795    0.0000 </r>
       <r>   11.7056    0.0000 </r>
       <r>   12.7867    0.0000 </r>
       <r>   12.9385    0.0000 </r>
       <r>   13.2788    0.0000 </r>
       <r>   14.1962    0.0000 </r>
       <r>   14.3599    0.0000 </r>
       <r>   14.7974    0.0000 </r>
      </set>
      <set comment="kpoint 12">
       <r>   -8.8343    1.0000 </r>
       <r>   -7.5176    1.0000 </r>
       <r>   -7.0713    1.0000 </r>
       <r>   -4.2603    1.0000 </r>
       <r>   -3.1885    1.0000 </r>
       <r>   -2.8901    1.0000 </r>
       <r>   -0.0254    1.0000 </r>
       <r>    0.0603    1.0000 </r>
       <r>    0.7987    1.0000 </r>
       <r>    1.4275    1.0000 </r>
       <r>    2.1202    1.0000 </r>
       <r>    2.5608    1.0000 </r>
       <r>    3.0712    1.0000 </r>
       <r>    3.2498    1.0000 </r>
       <r>    3.7978    1.0000 </r>
       <r>    4.3045    1.0000 </r>
       <r>    4.6152    1.0000 </r>
       <r>    4.9807    1.0000 </r>
       <r>    5.4055    1.0000 </r>
       <r>    5.7693    1.0000 </r>
       <r>    5.9827    1.0000 </r>
       <r>    6.3568    1.0000 </r>
       <r>    7.0681    1.0000 </r>
       <r>    7.3869    1.0000 </r>
       <r>   11.4882    0.0000 </r>
       <r>   12.1203    0.0000 </r>
       <r>   12.4500    0.0000 </r>
       <r>   12.9301    0.0000 </r>
       <r>   13.2592    0.0000 </r>
       <r>   13.5774    0.0000 </r>
       <r>   14.5276    0.0000 </r>
       <r>   14.8843    0.0000 </r>
      </set>
      <set comment="kpoint 13">
       <r>   -8.3460    1.0000 </r>
       <r>   -8.0087    1.0000 </r>
       <r>   -7.1005    1.0000 </r>
       <r>   -4.5220    1.0000 </r>
       <r>   -3.4878    1.0000 </r>
       <r>   -2.8374    1.0000 </r>
       <r>   -0.1707    1.0000 </r>
       <r>    0.5153    1.0000 </r>
       <r>    1.2895    1.0000 </r>
       <r>    1.7063    1.0000 </r>
       <r>    2.3555    1.0000 </r>
       <r>    2.6933    1.0000 </r>
       <r>    2.9285    1.0000 </r>
       <r>    3.6394    1.0000 </r>
       <r>    3.9452    1.0000 </r>
       <r>    4.0786    1.0000 </r>
       <r>    4.7322    1.0000 </r>
       <r>    4.9190    1.0000 </r>
       <r>    5.2899    1.0000 </r>
       <r>    5.5416    1.0000 </r>
       <r>    5.9074    1.0000 </r>
       <r>    6.4407    1.0000 </r>
       <r>    6.6199    1.0000 </r>
       <r>    7.2697    1.0000 </r>
       <r>   10.8019    0.0000 </r>
       <r>   11.8126    0.0000 </r>
       <r>   12.5773    0.0000 </r>
       <r>   12.9007    0.0000 </r>
       <r>   13.3199    0.0000 </r>
       <r>   13.6295    0.0000 </r>
       <r>   14.3195    0.0000 </r>
       <r>   14.4447    0.0000 </r>
      </set>
      <set comment="kpoint 14">
       <r>   -8.6649    1.0000 </r>
       <r>   -7.6607    1.0000 </r>
       <r>   -7.1763    1.0000 </r>
       <r>   -4.3921    1.0000 </r>
       <r>   -3.3882    1.0000 </r>
       <r>   -2.6421    1.0000 </r>
       <r>   -0.2052    1.0000 </r>
       <r>    0.7622    1.0000 </r>
       <r>    1.2457    1.0000 </r>
       <r>    1.5660    1.0000 </r>
       <r>    1.9484    1.0000 </r>
       <r>    2.3280    1.0000 </r>
       <r>    2.8188    1.0000 </r>
       <r>    3.4381    1.0000 </r>
       <r>    3.9010    1.0000 </r>
       <r>    4.2833    1.0000 </r>
       <r>    4.7869    1.0000 </r>
       <r>    5.0393    1.0000 </r>
       <r>    5.2519    1.0000 </r>
       <r>    5.3447    1.0000 </r>
       <r>    5.7724    1.0000 </r>
       <r>    6.1283    1.0000 </r>
       <r>    6.8844    1.0000 </r>
       <r>    7.2292    1.0000 </r>
       <r>   11.2792    0.0000 </r>
       <r>   11.7187    0.0000 </r>
       <r>   12.7495    0.0000 </r>
       <r>   13.0334    0.0000 </r>
       <r>   13.6169    0.0000 </r>
       <r>   14.0120    0.0000 </r>
       <r>   14.6773    0.0000 </r>
       <r>   14.7663    0.0000 </r>
      </set>
      <set comment="kpoint 15">
       <r>   -8.8741    1.0000 </r>
       <r>   -7.4567    1.0000 </r>
       <r>   -7.0185    1.0000 </r>
       <r>   -4.3976    1.0000 </r>
       <r>   -3.5090    1.0000 </r>
       <r>   -2.4661    1.0000 </r>
       <r>   -0.2368    1.0000 </r>
       <r>    0.3077    1.0000 </r>
       <r>    0.9241    1.0000 </r>
       <r>    1.3439    1.0000 </r>
       <r>    1.8934    1.0000 </r>
       <r>    2.5406    1.0000 </r>
       <r>    2.9955    1.0000 </r>
       <r>    3.4830    1.0000 </r>
       <r>    3.8228    1.0000 </r>
       <r>    4.4291    1.0000 </r>
       <r>    4.7430    1.0000 </r>
       <r>    4.7911    1.0000 </r>
       <r>    5.4165    1.0000 </r>
       <r>    5.6584    1.0000 </r>
       <r>    5.8855    1.0000 </r>
       <r>    6.2864    1.0000 </r>
       <r>    7.1398    1.0000 </r>
       <r>    7.4984    1.0000 </r>
       <r>   11.4607    0.0000 </r>
       <r>   11.9857    0.0000 </r>
       <r>   12.4880    0.0000 </r>
       <r>   12.8876    0.0000 </r>
       <r>   13.0361    0.0000 </r>
       <r>   13.8448    0.0000 </r>
       <r>   14.1797    0.0000 </r>
       <r>   14.9308    0.0000 </r>
      </set>
      <set comment="kpoint 16">
       <r>   -8.8978    1.0000 </r>
       <r>   -7.5077    1.0000 </r>
       <r>   -6.9756    1.0000 </r>
       <r>   -4.2807    1.0000 </r>
       <r>   -3.3135    1.0000 </r>
       <r>   -2.4072    1.0000 </r>
       <r>   -0.5500    1.0000 </r>
       <r>    0.0307    1.0000 </r>
       <r>    0.7072    1.0000 </r>
       <r>    1.1197    1.0000 </r>
       <r>    1.9500    1.0000 </r>
       <r>    2.6279    1.0000 </r>
       <r>    3.1645    1.0000 </r>
       <r>    3.4880    1.0000 </r>
       <r>    4.0984    1.0000 </r>
       <r>    4.2703    1.0000 </r>
       <r>    4.6036    1.0000 </r>
       <r>    5.1154    1.0000 </r>
       <r>    5.2913    1.0000 </r>
       <r>    5.5612    1.0000 </r>
       <r>    6.3239    1.0000 </r>
       <r>    6.4391    1.0000 </r>
       <r>    7.2299    1.0000 </r>
       <r>    7.5309    1.0000 </r>
       <r>   11.4778    0.0000 </r>
       <r>   12.0785    0.0000 </r>
       <r>   12.1929    0.0000 </r>
       <r>   12.8361    0.0000 </r>
       <r>   13.4569    0.0000 </r>
       <r>   13.6192    0.0000 </r>
       <r>   14.2409    0.0000 </r>
       <r>   14.7224    0.0000 </r>
      </set>
      <set comment="kpoint 17">
       <r>   -8.5124    1.0000 </r>
       <r>   -7.8912    1.0000 </r>
       <r>   -7.0045    1.0000 </r>
       <r>   -4.4448    1.0000 </r>
       <r>   -3.6604    1.0000 </r>
       <r>   -2.6134    1.0000 </r>
       <r>    0.0082    1.0000 </r>
       <r>    0.3031    1.0000 </r>
       <r>    0.7719    1.0000 </r>
       <r>    1.7385    1.0000 </r>
       <r>    2.0790    1.0000 </r>
       <r>    2.3883    1.0000 </r>
       <r>    3.2184    1.0000 </r>
       <r>    3.6357    1.0000 </r>
       <r>    3.8919    1.0000 </r>
       <r>    4.3221    1.0000 </r>
       <r>    4.7614    1.0000 </r>
       <r>    5.0852    1.0000 </r>
       <r>    5.2840    1.0000 </r>
       <r>    5.7457    1.0000 </r>
       <r>    6.0803    1.0000 </r>
       <r>    6.3441    1.0000 </r>
       <r>    7.0817    1.0000 </r>
       <r>    7.4233    1.0000 </r>
       <r>   10.9931    0.0000 </r>
       <r>   11.5825    0.0000 </r>
       <r>   12.1183    0.0000 </r>
       <r>   12.4023    0.0000 </r>
       <r>   13.0140    0.0000 </r>
       <r>   13.8865    0.0000 </r>
       <r>   14.0521    0.0000 </r>
       <r>   14.1833    0.0000 </r>
      </set>
      <set comment="kpoint 18">
       <r>   -8.4874    1.0000 </r>
       <r>   -7.8319    1.0000 </r>
       <r>   -7.0650    1.0000 </r>
       <r>   -4.5616    1.0000 </r>
       <r>   -3.8130    1.0000 </r>
       <r>   -2.6026    1.0000 </r>
       <r>    0.2137    1.0000 </r>
       <r>    0.5198    1.0000 </r>
       <r>    1.2423    1.0000 </r>
       <r>    1.6723    1.0000 </r>
       <r>    2.1522    1.0000 </r>
       <r>    2.3822    1.0000 </r>
       <r>    3.0148    1.0000 </r>
       <r>    3.5674    1.0000 </r>
       <r>    3.8380    1.0000 </r>
       <r>    4.2854    1.0000 </r>
       <r>    4.5812    1.0000 </r>
       <r>    4.9196    1.0000 </r>
       <r>    5.3891    1.0000 </r>
       <r>    5.6694    1.0000 </r>
       <r>    5.8795    1.0000 </r>
       <r>    6.4802    1.0000 </r>
       <r>    6.8638    1.0000 </r>
       <r>    7.3531    1.0000 </r>
       <r>   11.0478    0.0000 </r>
       <r>   11.5009    0.0000 </r>
       <r>   12.2586    0.0000 </r>
       <r>   12.5244    0.0000 </r>
       <r>   13.0844    0.0000 </r>
       <r>   13.2488    0.0000 </r>
       <r>   14.1939    0.0000 </r>
       <r>   14.5268    0.0000 </r>
      </set>
      <set comment="kpoint 19">
       <r>   -8.5917    1.0000 </r>
       <r>   -7.6553    1.0000 </r>
       <r>   -7.0915    1.0000 </r>
       <r>   -4.5235    1.0000 </r>
       <r>   -3.9797    1.0000 </r>
       <r>   -2.4610    1.0000 </r>
       <r>   -0.2075    1.0000 </r>
       <r>    0.3399    1.0000 </r>
       <r>    1.5001    1.0000 </r>
       <r>    1.8216    1.0000 </r>
       <r>    2.3515    1.0000 </r>
       <r>    2.6800    1.0000 </r>
       <r>    3.0790    1.0000 </r>
       <r>    3.4699    1.0000 </r>
       <r>    3.8426    1.0000 </r>
       <r>    4.3813    1.0000 </r>
       <r>    4.6386    1.0000 </r>
       <r>    5.0161    1.0000 </r>
       <r>    5.1066    1.0000 </r>
       <r>    5.4645    1.0000 </r>
       <r>    5.8188    1.0000 </r>
       <r>    6.4090    1.0000 </r>
       <r>    6.9005    1.0000 </r>
       <r>    7.1056    1.0000 </r>
       <r>   10.7517    0.0000 </r>
       <r>   11.7476    0.0000 </r>
       <r>   12.4565    0.0000 </r>
       <r>   12.9605    0.0000 </r>
       <r>   13.1123    0.0000 </r>
       <r>   13.7811    0.0000 </r>
       <r>   14.1100    0.0000 </r>
       <r>   14.4945    0.0000 </r>
      </set>
      <set comment="kpoint 20">
       <r>   -8.6280    1.0000 </r>
       <r>   -7.7005    1.0000 </r>
       <r>   -7.0168    1.0000 </r>
       <r>   -4.5830    1.0000 </r>
       <r>   -3.6633    1.0000 </r>
       <r>   -2.4833    1.0000 </r>
       <r>   -0.2686    1.0000 </r>
       <r>    0.3220    1.0000 </r>
       <r>    0.9357    1.0000 </r>
       <r>    1.6216    1.0000 </r>
       <r>    2.0863    1.0000 </r>
       <r>    2.4678    1.0000 </r>
       <r>    3.3366    1.0000 </r>
       <r>    3.6398    1.0000 </r>
       <r>    4.1233    1.0000 </r>
       <r>    4.3916    1.0000 </r>
       <r>    4.6262    1.0000 </r>
       <r>    5.0092    1.0000 </r>
       <r>    5.2874    1.0000 </r>
       <r>    5.7106    1.0000 </r>
       <r>    5.9076    1.0000 </r>
       <r>    6.4595    1.0000 </r>
       <r>    7.1711    1.0000 </r>
       <r>    7.3417    1.0000 </r>
       <r>   10.9851    0.0000 </r>
       <r>   11.4087    0.0000 </r>
       <r>   12.0123    0.0000 </r>
       <r>   12.4711    0.0000 </r>
       <r>   13.1644    0.0000 </r>
       <r>   13.5702    0.0000 </r>
       <r>   13.8669    0.0000 </r>
       <r>   14.5168    0.0000 </r>
      </set>
      <set comment="kpoint 21">
       <r>   -8.4249    1.0000 </r>
       <r>   -7.9209    1.0000 </r>
       <r>   -7.1059    1.0000 </r>
       <r>   -4.4725    1.0000 </r>
       <r>   -3.5216    1.0000 </r>
       <r>   -2.8152    1.0000 </r>
       <r>   -0.3869    1.0000 </r>
       <r>    0.6403    1.0000 </r>
       <r>    1.3091    1.0000 </r>
       <r>    1.5557    1.0000 </r>
       <r>    2.3380    1.0000 </r>
       <r>    2.7161    1.0000 </r>
       <r>    3.3868    1.0000 </r>
       <r>    3.5277    1.0000 </r>
       <r>    3.9978    1.0000 </r>
       <r>    4.1378    1.0000 </r>
       <r>    4.5002    1.0000 </r>
       <r>    4.8544    1.0000 </r>
       <r>    5.3791    1.0000 </r>
       <r>    5.5480    1.0000 </r>
       <r>    5.8812    1.0000 </r>
       <r>    6.2570    1.0000 </r>
       <r>    6.8581    1.0000 </r>
       <r>    7.1816    1.0000 </r>
       <r>   10.7563    0.0000 </r>
       <r>   11.5473    0.0000 </r>
       <r>   12.6388    0.0000 </r>
       <r>   12.9174    0.0000 </r>
       <r>   13.3292    0.0000 </r>
       <r>   13.8333    0.0000 </r>
       <r>   14.2812    0.0000 </r>
       <r>   14.6753    0.0000 </r>
      </set>
      <set comment="kpoint 22">
       <r>   -8.4056    1.0000 </r>
       <r>   -7.8370    1.0000 </r>
       <r>   -7.1895    1.0000 </r>
       <r>   -4.4757    1.0000 </r>
       <r>   -3.8992    1.0000 </r>
       <r>   -2.7236    1.0000 </r>
       <r>    0.0779    1.0000 </r>
       <r>    0.8167    1.0000 </r>
       <r>    1.5875    1.0000 </r>
       <r>    1.9114    1.0000 </r>
       <r>    2.3527    1.0000 </r>
       <r>    2.5167    1.0000 </r>
       <r>    2.8641    1.0000 </r>
       <r>    3.3256    1.0000 </r>
       <r>    3.6268    1.0000 </r>
       <r>    4.2593    1.0000 </r>
       <r>    4.5460    1.0000 </r>
       <r>    4.7792    1.0000 </r>
       <r>    5.2810    1.0000 </r>
       <r>    5.7413    1.0000 </r>
       <r>    5.9320    1.0000 </r>
       <r>    6.2172    1.0000 </r>
       <r>    6.7076    1.0000 </r>
       <r>    7.2672    1.0000 </r>
       <r>   11.2092    0.0000 </r>
       <r>   11.5027    0.0000 </r>
       <r>   12.1506    0.0000 </r>
       <r>   12.4900    0.0000 </r>
       <r>   12.7080    0.0000 </r>
       <r>   13.5490    0.0000 </r>
       <r>   14.3594    0.0000 </r>
       <r>   14.8437    0.0000 </r>
      </set>
      <set comment="kpoint 23">
       <r>   -8.7314    1.0000 </r>
       <r>   -7.5287    1.0000 </r>
       <r>   -7.1960    1.0000 </r>
       <r>   -4.1173    1.0000 </r>
       <r>   -3.9495    1.0000 </r>
       <r>   -2.4240    1.0000 </r>
       <r>   -0.1701    1.0000 </r>
       <r>    0.4198    1.0000 </r>
       <r>    1.4083    1.0000 </r>
       <r>    1.6884    1.0000 </r>
       <r>    2.1203    1.0000 </r>
       <r>    2.5484    1.0000 </r>
       <r>    2.7426    1.0000 </r>
       <r>    3.3575    1.0000 </r>
       <r>    3.7020    1.0000 </r>
       <r>    4.3303    1.0000 </r>
       <r>    4.6019    1.0000 </r>
       <r>    5.1236    1.0000 </r>
       <r>    5.2235    1.0000 </r>
       <r>    5.4299    1.0000 </r>
       <r>    5.8262    1.0000 </r>
       <r>    6.2905    1.0000 </r>
       <r>    6.6455    1.0000 </r>
       <r>    7.2875    1.0000 </r>
       <r>   11.3796    0.0000 </r>
       <r>   11.5942    0.0000 </r>
       <r>   12.6934    0.0000 </r>
       <r>   13.0091    0.0000 </r>
       <r>   13.5162    0.0000 </r>
       <r>   14.0897    0.0000 </r>
       <r>   14.4491    0.0000 </r>
       <r>   14.7368    0.0000 </r>
      </set>
      <set comment="kpoint 24">
       <r>   -8.5239    1.0000 </r>
       <r>   -7.7527    1.0000 </r>
       <r>   -7.1171    1.0000 </r>
       <r>   -4.5418    1.0000 </r>
       <r>   -3.7426    1.0000 </r>
       <r>   -2.6523    1.0000 </r>
       <r>    0.1389    1.0000 </r>
       <r>    0.2886    1.0000 </r>
       <r>    1.1470    1.0000 </r>
       <r>    1.8052    1.0000 </r>
       <r>    2.2682    1.0000 </r>
       <r>    2.6427    1.0000 </r>
       <r>    3.0445    1.0000 </r>
       <r>    3.5332    1.0000 </r>
       <r>    3.8302    1.0000 </r>
       <r>    4.2202    1.0000 </r>
       <r>    4.5405    1.0000 </r>
       <r>    4.9441    1.0000 </r>
       <r>    5.4320    1.0000 </r>
       <r>    5.6212    1.0000 </r>
       <r>    6.1028    1.0000 </r>
       <r>    6.4391    1.0000 </r>
       <r>    6.6851    1.0000 </r>
       <r>    7.3256    1.0000 </r>
       <r>   11.2659    0.0000 </r>
       <r>   11.4515    0.0000 </r>
       <r>   12.0575    0.0000 </r>
       <r>   12.4566    0.0000 </r>
       <r>   12.7323    0.0000 </r>
       <r>   13.7348    0.0000 </r>
       <r>   14.0848    0.0000 </r>
       <r>   14.7343    0.0000 </r>
      </set>
      <set comment="kpoint 25">
       <r>   -8.2330    1.0000 </r>
       <r>   -8.0411    1.0000 </r>
       <r>   -7.2090    1.0000 </r>
       <r>   -4.5918    1.0000 </r>
       <r>   -3.3981    1.0000 </r>
       <r>   -2.9855    1.0000 </r>
       <r>   -0.1177    1.0000 </r>
       <r>    0.9207    1.0000 </r>
       <r>    1.4782    1.0000 </r>
       <r>    1.8579    1.0000 </r>
       <r>    2.2280    1.0000 </r>
       <r>    2.6883    1.0000 </r>
       <r>    2.9314    1.0000 </r>
       <r>    3.3553    1.0000 </r>
       <r>    3.5349    1.0000 </r>
       <r>    4.3298    1.0000 </r>
       <r>    4.7239    1.0000 </r>
       <r>    4.9722    1.0000 </r>
       <r>    5.3260    1.0000 </r>
       <r>    5.4537    1.0000 </r>
       <r>    5.8839    1.0000 </r>
       <r>    6.1944    1.0000 </r>
       <r>    6.7207    1.0000 </r>
       <r>    7.2422    1.0000 </r>
       <r>   11.3604    0.0000 </r>
       <r>   11.5692    0.0000 </r>
       <r>   12.1801    0.0000 </r>
       <r>   12.2079    0.0000 </r>
       <r>   12.9788    0.0000 </r>
       <r>   13.3016    0.0000 </r>
       <r>   14.3552    0.0000 </r>
       <r>   14.7910    0.0000 </r>
      </set>
      <set comment="kpoint 26">
       <r>   -8.5970    1.0000 </r>
       <r>   -7.6821    1.0000 </r>
       <r>   -7.2600    1.0000 </r>
       <r>   -4.2747    1.0000 </r>
       <r>   -3.5046    1.0000 </r>
       <r>   -2.8438    1.0000 </r>
       <r>   -0.0873    1.0000 </r>
       <r>    0.9131    1.0000 </r>
       <r>    1.3994    1.0000 </r>
       <r>    1.8184    1.0000 </r>
       <r>    2.2074    1.0000 </r>
       <r>    2.4793    1.0000 </r>
       <r>    2.8666    1.0000 </r>
       <r>    3.3078    1.0000 </r>
       <r>    3.7329    1.0000 </r>
       <r>    4.0888    1.0000 </r>
       <r>    4.4905    1.0000 </r>
       <r>    4.8527    1.0000 </r>
       <r>    5.1569    1.0000 </r>
       <r>    5.5458    1.0000 </r>
       <r>    5.6691    1.0000 </r>
       <r>    6.0606    1.0000 </r>
       <r>    6.6677    1.0000 </r>
       <r>    7.1781    1.0000 </r>
       <r>   11.3431    0.0000 </r>
       <r>   11.9455    0.0000 </r>
       <r>   12.6716    0.0000 </r>
       <r>   13.1640    0.0000 </r>
       <r>   13.7465    0.0000 </r>
       <r>   13.8482    0.0000 </r>
       <r>   14.2909    0.0000 </r>
       <r>   14.5206    0.0000 </r>
      </set>
      <set comment="kpoint 27">
       <r>   -8.7566    1.0000 </r>
       <r>   -7.6569    1.0000 </r>
       <r>   -7.1415    1.0000 </r>
       <r>   -4.2673    1.0000 </r>
       <r>   -3.2472    1.0000 </r>
       <r>   -2.7577    1.0000 </r>
       <r>    0.2982    1.0000 </r>
       <r>    0.9291    1.0000 </r>
       <r>    1.2125    1.0000 </r>
       <r>    1.4669    1.0000 </r>
       <r>    1.9046    1.0000 </r>
       <r>    2.2725    1.0000 </r>
       <r>    2.9610    1.0000 </r>
       <r>    3.1788    1.0000 </r>
       <r>    3.6361    1.0000 </r>
       <r>    3.7714    1.0000 </r>
       <r>    4.4691    1.0000 </r>
       <r>    4.7107    1.0000 </r>
       <r>    4.9131    1.0000 </r>
       <r>    5.5502    1.0000 </r>
       <r>    5.8188    1.0000 </r>
       <r>    6.0327    1.0000 </r>
       <r>    7.2903    1.0000 </r>
       <r>    7.3904    1.0000 </r>
       <r>   11.1358    0.0000 </r>
       <r>   11.2158    0.0000 </r>
       <r>   12.3077    0.0000 </r>
       <r>   13.7491    0.0000 </r>
       <r>   14.4934    0.0000 </r>
       <r>   14.5701    0.0000 </r>
       <r>   14.7804    0.0000 </r>
       <r>   15.2057    0.0000 </r>
      </set>
      <set comment="kpoint 28">
       <r>   -8.5945    1.0000 </r>
       <r>   -7.7135    1.0000 </r>
       <r>   -7.1971    1.0000 </r>
       <r>   -4.4060    1.0000 </r>
       <r>   -3.5107    1.0000 </r>
       <r>   -2.7759    1.0000 </r>
       <r>    0.1578    1.0000 </r>
       <r>    0.8472    1.0000 </r>
       <r>    1.1183    1.0000 </r>
       <r>    1.9092    1.0000 </r>
       <r>    2.2284    1.0000 </r>
       <r>    2.5816    1.0000 </r>
       <r>    2.9586    1.0000 </r>
       <r>    3.2302    1.0000 </r>
       <r>    3.7391    1.0000 </r>
       <r>    4.0702    1.0000 </r>
       <r>    4.5460    1.0000 </r>
       <r>    4.7425    1.0000 </r>
       <r>    5.2091    1.0000 </r>
       <r>    5.3538    1.0000 </r>
       <r>    5.7227    1.0000 </r>
       <r>    5.9473    1.0000 </r>
       <r>    6.8204    1.0000 </r>
       <r>    7.1465    1.0000 </r>
       <r>   11.4157    0.0000 </r>
       <r>   12.0144    0.0000 </r>
       <r>   12.9277    0.0000 </r>
       <r>   13.0210    0.0000 </r>
       <r>   13.5524    0.0000 </r>
       <r>   13.8297    0.0000 </r>
       <r>   14.3534    0.0000 </r>
       <r>   14.6427    0.0000 </r>
      </set>
      <set comment="kpoint 29">
       <r>   -8.1804    1.0000 </r>
       <r>   -8.1370    1.0000 </r>
       <r>   -7.1152    1.0000 </r>
       <r>   -4.5803    1.0000 </r>
       <r>   -3.4882    1.0000 </r>
       <r>   -3.1742    1.0000 </r>
       <r>    0.3587    1.0000 </r>
       <r>    0.9008    1.0000 </r>
       <r>    1.4119    1.0000 </r>
       <r>    1.8519    1.0000 </r>
       <r>    2.2094    1.0000 </r>
       <r>    2.7551    1.0000 </r>
       <r>    3.0339    1.0000 </r>
       <r>    3.4923    1.0000 </r>
       <r>    3.7539    1.0000 </r>
       <r>    4.1410    1.0000 </r>
       <r>    4.4698    1.0000 </r>
       <r>    4.7553    1.0000 </r>
       <r>    5.2082    1.0000 </r>
       <r>    5.2652    1.0000 </r>
       <r>    5.7218    1.0000 </r>
       <r>    6.4148    1.0000 </r>
       <r>    6.5440    1.0000 </r>
       <r>    7.2940    1.0000 </r>
       <r>   11.1060    0.0000 </r>
       <r>   12.1953    0.0000 </r>
       <r>   12.4813    0.0000 </r>
       <r>   12.7907    0.0000 </r>
       <r>   12.9952    0.0000 </r>
       <r>   13.4866    0.0000 </r>
       <r>   14.2916    0.0000 </r>
       <r>   14.5483    0.0000 </r>
      </set>
      <set comment="kpoint 30">
       <r>   -8.6529    1.0000 </r>
       <r>   -7.6509    1.0000 </r>
       <r>   -7.1339    1.0000 </r>
       <r>   -4.3986    1.0000 </r>
       <r>   -3.8601    1.0000 </r>
       <r>   -2.5194    1.0000 </r>
       <r>    0.1623    1.0000 </r>
       <r>    0.9008    1.0000 </r>
       <r>    1.3200    1.0000 </r>
       <r>    1.8713    1.0000 </r>
       <r>    2.2492    1.0000 </r>
       <r>    2.3246    1.0000 </r>
       <r>    2.9173    1.0000 </r>
       <r>    3.5254    1.0000 </r>
       <r>    3.7198    1.0000 </r>
       <r>    3.9955    1.0000 </r>
       <r>    4.2694    1.0000 </r>
       <r>    4.7328    1.0000 </r>
       <r>    5.0178    1.0000 </r>
       <r>    5.4521    1.0000 </r>
       <r>    5.7489    1.0000 </r>
       <r>    6.2526    1.0000 </r>
       <r>    6.8064    1.0000 </r>
       <r>    7.1216    1.0000 </r>
       <r>   11.3351    0.0000 </r>
       <r>   12.0470    0.0000 </r>
       <r>   12.5987    0.0000 </r>
       <r>   12.9780    0.0000 </r>
       <r>   13.4614    0.0000 </r>
       <r>   14.0122    0.0000 </r>
       <r>   14.5166    0.0000 </r>
       <r>   14.6575    0.0000 </r>
      </set>
      <set comment="kpoint 31">
       <r>   -8.6877    1.0000 </r>
       <r>   -7.6602    1.0000 </r>
       <r>   -7.1223    1.0000 </r>
       <r>   -4.4357    1.0000 </r>
       <r>   -3.4029    1.0000 </r>
       <r>   -2.6170    1.0000 </r>
       <r>   -0.3016    1.0000 </r>
       <r>    0.6913    1.0000 </r>
       <r>    1.2074    1.0000 </r>
       <r>    1.7252    1.0000 </r>
       <r>    2.0176    1.0000 </r>
       <r>    2.4597    1.0000 </r>
       <r>    3.0345    1.0000 </r>
       <r>    3.4091    1.0000 </r>
       <r>    3.7180    1.0000 </r>
       <r>    4.3225    1.0000 </r>
       <r>    4.6262    1.0000 </r>
       <r>    4.8877    1.0000 </r>
       <r>    5.2236    1.0000 </r>
       <r>    5.4118    1.0000 </r>
       <r>    5.7613    1.0000 </r>
       <r>    6.0592    1.0000 </r>
       <r>    7.0504    1.0000 </r>
       <r>    7.2020    1.0000 </r>
       <r>   11.4074    0.0000 </r>
       <r>   11.5547    0.0000 </r>
       <r>   12.7270    0.0000 </r>
       <r>   13.0305    0.0000 </r>
       <r>   13.7114    0.0000 </r>
       <r>   14.2295    0.0000 </r>
       <r>   14.3691    0.0000 </r>
       <r>   14.6502    0.0000 </r>
      </set>
      <set comment="kpoint 32">
       <r>   -8.4214    1.0000 </r>
       <r>   -7.9473    1.0000 </r>
       <r>   -7.0310    1.0000 </r>
       <r>   -4.5898    1.0000 </r>
       <r>   -3.6507    1.0000 </r>
       <r>   -2.7014    1.0000 </r>
       <r>    0.0194    1.0000 </r>
       <r>    0.7974    1.0000 </r>
       <r>    1.0369    1.0000 </r>
       <r>    1.7165    1.0000 </r>
       <r>    2.0733    1.0000 </r>
       <r>    2.4985    1.0000 </r>
       <r>    2.9512    1.0000 </r>
       <r>    3.5189    1.0000 </r>
       <r>    3.8475    1.0000 </r>
       <r>    4.5254    1.0000 </r>
       <r>    4.7248    1.0000 </r>
       <r>    4.9225    1.0000 </r>
       <r>    5.3754    1.0000 </r>
       <r>    5.5611    1.0000 </r>
       <r>    5.8305    1.0000 </r>
       <r>    6.2784    1.0000 </r>
       <r>    6.9523    1.0000 </r>
       <r>    7.3539    1.0000 </r>
       <r>   11.1559    0.0000 </r>
       <r>   11.6895    0.0000 </r>
       <r>   12.1707    0.0000 </r>
       <r>   12.4686    0.0000 </r>
       <r>   12.7662    0.0000 </r>
       <r>   13.3350    0.0000 </r>
       <r>   14.0717    0.0000 </r>
       <r>   14.7111    0.0000 </r>
      </set>
      <set comment="kpoint 33">
       <r>   -8.3902    1.0000 </r>
       <r>   -7.9050    1.0000 </r>
       <r>   -7.0782    1.0000 </r>
       <r>   -4.5141    1.0000 </r>
       <r>   -4.1517    1.0000 </r>
       <r>   -2.4561    1.0000 </r>
       <r>    0.3512    1.0000 </r>
       <r>    0.5379    1.0000 </r>
       <r>    1.5420    1.0000 </r>
       <r>    1.8918    1.0000 </r>
       <r>    2.3031    1.0000 </r>
       <r>    2.6944    1.0000 </r>
       <r>    2.8832    1.0000 </r>
       <r>    3.2619    1.0000 </r>
       <r>    3.6421    1.0000 </r>
       <r>    4.0328    1.0000 </r>
       <r>    4.6403    1.0000 </r>
       <r>    4.8277    1.0000 </r>
       <r>    5.3375    1.0000 </r>
       <r>    5.5434    1.0000 </r>
       <r>    6.0683    1.0000 </r>
       <r>    6.3081    1.0000 </r>
       <r>    6.6268    1.0000 </r>
       <r>    7.2606    1.0000 </r>
       <r>   11.1976    0.0000 </r>
       <r>   11.6703    0.0000 </r>
       <r>   12.1154    0.0000 </r>
       <r>   12.5673    0.0000 </r>
       <r>   12.9178    0.0000 </r>
       <r>   13.0289    0.0000 </r>
       <r>   14.3772    0.0000 </r>
       <r>   14.6896    0.0000 </r>
      </set>
      <set comment="kpoint 34">
       <r>   -8.5115    1.0000 </r>
       <r>   -7.7521    1.0000 </r>
       <r>   -7.0326    1.0000 </r>
       <r>   -4.5868    1.0000 </r>
       <r>   -4.1711    1.0000 </r>
       <r>   -2.6319    1.0000 </r>
       <r>    0.1824    1.0000 </r>
       <r>    1.1179    1.0000 </r>
       <r>    1.5971    1.0000 </r>
       <r>    2.0087    1.0000 </r>
       <r>    2.1744    1.0000 </r>
       <r>    2.9116    1.0000 </r>
       <r>    3.0651    1.0000 </r>
       <r>    3.3608    1.0000 </r>
       <r>    3.4020    1.0000 </r>
       <r>    4.0575    1.0000 </r>
       <r>    4.4404    1.0000 </r>
       <r>    4.6975    1.0000 </r>
       <r>    4.9375    1.0000 </r>
       <r>    5.3789    1.0000 </r>
       <r>    5.8264    1.0000 </r>
       <r>    6.4191    1.0000 </r>
       <r>    6.7991    1.0000 </r>
       <r>    7.2335    1.0000 </r>
       <r>   10.9658    0.0000 </r>
       <r>   11.9950    0.0000 </r>
       <r>   12.3450    0.0000 </r>
       <r>   12.9353    0.0000 </r>
       <r>   13.1749    0.0000 </r>
       <r>   13.6092    0.0000 </r>
       <r>   13.9636    0.0000 </r>
       <r>   14.6245    0.0000 </r>
      </set>
      <set comment="kpoint 35">
       <r>   -8.5270    1.0000 </r>
       <r>   -7.8109    1.0000 </r>
       <r>   -6.9969    1.0000 </r>
       <r>   -4.6237    1.0000 </r>
       <r>   -3.8823    1.0000 </r>
       <r>   -2.5101    1.0000 </r>
       <r>    0.0481    1.0000 </r>
       <r>    0.8504    1.0000 </r>
       <r>    0.9361    1.0000 </r>
       <r>    1.7021    1.0000 </r>
       <r>    2.1378    1.0000 </r>
       <r>    2.8090    1.0000 </r>
       <r>    2.9204    1.0000 </r>
       <r>    3.4341    1.0000 </r>
       <r>    3.8896    1.0000 </r>
       <r>    4.2058    1.0000 </r>
       <r>    4.5218    1.0000 </r>
       <r>    4.9991    1.0000 </r>
       <r>    5.3396    1.0000 </r>
       <r>    5.6325    1.0000 </r>
       <r>    5.9215    1.0000 </r>
       <r>    6.2193    1.0000 </r>
       <r>    7.1014    1.0000 </r>
       <r>    7.3466    1.0000 </r>
       <r>   11.1627    0.0000 </r>
       <r>   11.5272    0.0000 </r>
       <r>   12.2244    0.0000 </r>
       <r>   12.3962    0.0000 </r>
       <r>   12.5894    0.0000 </r>
       <r>   13.6094    0.0000 </r>
       <r>   14.1495    0.0000 </r>
       <r>   14.9162    0.0000 </r>
      </set>
      <set comment="kpoint 36">
       <r>   -8.5163    1.0000 </r>
       <r>   -7.9151    1.0000 </r>
       <r>   -6.9541    1.0000 </r>
       <r>   -4.5866    1.0000 </r>
       <r>   -3.4873    1.0000 </r>
       <r>   -2.4953    1.0000 </r>
       <r>   -0.5521    1.0000 </r>
       <r>    0.2814    1.0000 </r>
       <r>    1.2333    1.0000 </r>
       <r>    1.3369    1.0000 </r>
       <r>    2.1431    1.0000 </r>
       <r>    2.7082    1.0000 </r>
       <r>    3.3098    1.0000 </r>
       <r>    3.6575    1.0000 </r>
       <r>    3.9697    1.0000 </r>
       <r>    4.5168    1.0000 </r>
       <r>    4.7893    1.0000 </r>
       <r>    5.0633    1.0000 </r>
       <r>    5.3141    1.0000 </r>
       <r>    5.6239    1.0000 </r>
       <r>    5.7823    1.0000 </r>
       <r>    6.2173    1.0000 </r>
       <r>    7.0848    1.0000 </r>
       <r>    7.3813    1.0000 </r>
       <r>   10.7412    0.0000 </r>
       <r>   11.5739    0.0000 </r>
       <r>   12.8652    0.0000 </r>
       <r>   12.9921    0.0000 </r>
       <r>   13.2235    0.0000 </r>
       <r>   13.6095    0.0000 </r>
       <r>   13.9422    0.0000 </r>
       <r>   14.2178    0.0000 </r>
      </set>
     </set>
    </set>
   </array>
  </eigenvalues>
  <separator name="orbital magnetization" >
   <v name="MAGDIPOLOUT">      0.00000000      0.00000000      0.00000000</v>
  </separator>
  <dos>
   <i name="efermi">      8.12735954 </i>
   <total>
    <array>
     <dimension dim="1">gridpoints</dimension>
     <dimension dim="2">spin</dimension>
     <field>energy</field>
     <field>total</field>
     <field>integrated</field>
     <set>
      <set comment="spin 1">
       <r>   -10.3397     0.0000     0.0000 </r>
       <r>   -10.2504     0.0000     0.0000 </r>
       <r>   -10.1612     0.0000     0.0000 </r>
       <r>   -10.0720     0.0000     0.0000 </r>
       <r>    -9.9828     0.0000     0.0000 </r>
       <r>    -9.8936     0.0000     0.0000 </r>
       <r>    -9.8044     0.0000     0.0000 </r>
       <r>    -9.7152     0.0000     0.0000 </r>
       <r>    -9.6260     0.0000     0.0000 </r>
       <r>    -9.5368     0.0000     0.0000 </r>
       <r>    -9.4476     0.0000     0.0000 </r>
       <r>    -9.3584     0.0002     0.0000 </r>
       <r>    -9.2692     0.0067     0.0006 </r>
       <r>    -9.1800     0.0683     0.0067 </r>
       <r>    -9.0908     0.2035     0.0248 </r>
       <r>    -9.0016     0.5048     0.0699 </r>
       <r>    -8.9124     1.4621     0.2003 </r>
       <r>    -8.8232     2.1061     0.3882 </r>
       <r>    -8.7339     1.8701     0.5550 </r>
       <r>    -8.6447     2.6205     0.7888 </r>
       <r>    -8.5555     3.6626     1.1155 </r>
       <r>    -8.4663     3.6154     1.4380 </r>
       <r>    -8.3771     2.9893     1.7047 </r>
       <r>    -8.2879     1.8855     1.8729 </r>
       <r>    -8.1987     1.0058     1.9626 </r>
       <r>    -8.1095     0.7978     2.0338 </r>
       <r>    -8.0203     1.3120     2.1508 </r>
       <r>    -7.9311     2.3819     2.3633 </r>
       <r>    -7.8419     2.7286     2.6067 </r>
       <r>    -7.7527     2.7411     2.8512 </r>
       <r>    -7.6635     3.6392     3.1759 </r>
       <r>    -7.5743     3.2416     3.4650 </r>
       <r>    -7.4851     2.4630     3.6847 </r>
       <r>    -7.3959     1.9928     3.8625 </r>
       <r>    -7.3067     1.5662     4.0022 </r>
       <r>    -7.2174     3.0956     4.2784 </r>
       <r>    -7.1282     6.1690     4.8287 </r>
       <r>    -7.0390     7.1724     5.4685 </r>
       <r>    -6.9498     4.5136     5.8711 </r>
       <r>    -6.8606     1.3022     5.9873 </r>
       <r>    -6.7714     0.1377     5.9996 </r>
       <r>    -6.6822     0.0045     6.0000 </r>
       <r>    -6.5930     0.0000     6.0000 </r>
       <r>    -6.5038     0.0000     6.0000 </r>
       <r>    -6.4146     0.0000     6.0000 </r>
       <r>    -6.3254     0.0000     6.0000 </r>
       <r>    -6.2362     0.0000     6.0000 </r>
       <r>    -6.1470     0.0000     6.0000 </r>
       <r>    -6.0578     0.0000     6.0000 </r>
       <r>    -5.9686     0.0000     6.0000 </r>
       <r>    -5.8794     0.0000     6.0000 </r>
       <r>    -5.7902     0.0000     6.0000 </r>
       <r>    -5.7009     0.0000     6.0000 </r>
       <r>    -5.6117     0.0000     6.0000 </r>
       <r>    -5.5225     0.0000     6.0000 </r>
       <r>    -5.4333     0.0000     6.0000 </r>
       <r>    -5.3441     0.0000     6.0000 </r>
       <r>    -5.2549     0.0000     6.0000 </r>
       <r>    -5.1657     0.0000     6.0000 </r>
       <r>    -5.0765     0.0000     6.0000 </r>
       <r>    -4.9873     0.0000     6.0000 </r>
       <r>    -4.8981     0.0001     6.0000 </r>
       <r>    -4.8089     0.0060     6.0005 </r>
       <r>    -4.7197     0.1710     6.0158 </r>
       <r>    -4.6305     1.3791     6.1388 </r>
       <r>    -4.5413     3.7989     6.4777 </r>
       <r>    -4.4521     4.9454     6.9189 </r>
       <r>    -4.3629     4.1550     7.2895 </r>
       <r>    -4.2737     2.9001     7.5482 </r>
       <r>    -4.1844     2.5810     7.7785 </r>
       <r>    -4.0952     2.0722     7.9633 </r>
       <r>    -4.0060     1.5320     8.1000 </r>
       <r>    -3.9168     1.6173     8.2442 </r>
       <r>    -3.8276     1.7253     8.3982 </r>
       <r>    -3.7384     1.6442     8.5448 </r>
       <r>    -3.6492     1.9368     8.7176 </r>
       <r>    -3.5600     2.1290     8.9075 </r>
       <r>    -3.4708     3.0884     9.1830 </r>
       <r>    -3.3816     3.3331     9.4803 </r>
       <r>    -3.2924     2.3163     9.6870 </r>
       <r>    -3.2032     1.4721     9.8183 </r>
       <r>    -3.1140     1.4408     9.9468 </r>
       <r>    -3.0248     1.3647    10.0686 </r>
       <r>    -2.9356     1.2869    10.1834 </r>
       <r>    -2.8464     2.1298    10.3733 </r>
       <r>    -2.7572     3.2226    10.6608 </r>
       <r>    -2.6679     3.6225    10.9840 </r>
       <r>    -2.5787     3.4279    11.2898 </r>
       <r>    -2.4895     3.1471    11.5705 </r>
       <r>    -2.4003     2.9497    11.8336 </r>
       <r>    -2.3111     1.5170    11.9690 </r>
       <r>    -2.2219     0.3236    11.9978 </r>
       <r>    -2.1327     0.0239    12.0000 </r>
       <r>    -2.0435     0.0005    12.0000 </r>
       <r>    -1.9543     0.0000    12.0000 </r>
       <r>    -1.8651     0.0000    12.0000 </r>
       <r>    -1.7759     0.0000    12.0000 </r>
       <r>    -1.6867     0.0000    12.0000 </r>
       <r>    -1.5975     0.0000    12.0000 </r>
       <r>    -1.5083     0.0000    12.0000 </r>
       <r>    -1.4191     0.0000    12.0000 </r>
       <r>    -1.3299     0.0000    12.0000 </r>
       <r>    -1.2407     0.0000    12.0000 </r>
       <r>    -1.1514     0.0000    12.0000 </r>
       <r>    -1.0622     0.0000    12.0000 </r>
       <r>    -0.9730     0.0000    12.0000 </r>
       <r>    -0.8838     0.0000    12.0000 </r>
       <r>    -0.7946     0.0007    12.0001 </r>
       <r>    -0.7054     0.0327    12.0030 </r>
       <r>    -0.6162     0.3592    12.0350 </r>
       <r>    -0.5270     1.0773    12.1311 </r>
       <r>    -0.4378     1.3115    12.2481 </r>
       <r>    -0.3486     1.6174    12.3924 </r>
       <r>    -0.2594     2.5755    12.6222 </r>
       <r>    -0.1702     3.5161    12.9358 </r>
       <r>    -0.0810     3.7247    13.2681 </r>
       <r>     0.0082     3.5850    13.5879 </r>
       <r>     0.0974     3.1230    13.8665 </r>
       <r>     0.1866     2.7362    14.1106 </r>
       <r>     0.2758     3.3646    14.4107 </r>
       <r>     0.3651     3.9412    14.7623 </r>
       <r>     0.4543     2.4903    14.9844 </r>
       <r>     0.5435     1.5196    15.1200 </r>
       <r>     0.6327     1.5025    15.2540 </r>
       <r>     0.7219     2.2359    15.4535 </r>
       <r>     0.8111     3.5152    15.7670 </r>
       <r>     0.9003     4.3685    16.1567 </r>
       <r>     0.9895     3.8400    16.4993 </r>
       <r>     1.0787     3.1607    16.7812 </r>
       <r>     1.1679     3.6474    17.1066 </r>
       <r>     1.2571     3.7266    17.4390 </r>
       <r>     1.3463     3.9086    17.7877 </r>
       <r>     1.4355     3.7845    18.1253 </r>
       <r>     1.5247     3.3723    18.4261 </r>
       <r>     1.6139     3.6320    18.7501 </r>
       <r>     1.7031     4.3137    19.1349 </r>
       <r>     1.7923     4.6160    19.5467 </r>
       <r>     1.8816     4.7704    19.9723 </r>
       <r>     1.9708     4.5828    20.3811 </r>
       <r>     2.0600     3.9066    20.7296 </r>
       <r>     2.1492     4.2320    21.1071 </r>
       <r>     2.2384     4.5296    21.5112 </r>
       <r>     2.3276     4.7306    21.9332 </r>
       <r>     2.4168     4.7247    22.3546 </r>
       <r>     2.5060     4.9509    22.7963 </r>
       <r>     2.5952     4.9833    23.2408 </r>
       <r>     2.6844     4.5720    23.6487 </r>
       <r>     2.7736     4.3356    24.0354 </r>
       <r>     2.8628     4.5938    24.4452 </r>
       <r>     2.9520     5.2213    24.9110 </r>
       <r>     3.0412     4.3351    25.2977 </r>
       <r>     3.1304     3.0143    25.5666 </r>
       <r>     3.2196     2.8216    25.8183 </r>
       <r>     3.3088     3.7963    26.1570 </r>
       <r>     3.3981     4.8679    26.5912 </r>
       <r>     3.4873     5.5059    27.0824 </r>
       <r>     3.5765     5.7739    27.5974 </r>
       <r>     3.6657     5.8281    28.1173 </r>
       <r>     3.7549     5.5500    28.6124 </r>
       <r>     3.8441     5.1030    29.0676 </r>
       <r>     3.9333     4.9970    29.5134 </r>
       <r>     4.0225     4.5846    29.9224 </r>
       <r>     4.1117     4.3410    30.3096 </r>
       <r>     4.2009     4.6172    30.7215 </r>
       <r>     4.2901     5.8588    31.2442 </r>
       <r>     4.3793     5.5950    31.7433 </r>
       <r>     4.4685     4.6078    32.1543 </r>
       <r>     4.5577     5.7707    32.6691 </r>
       <r>     4.6469     6.5302    33.2516 </r>
       <r>     4.7361     6.4946    33.8310 </r>
       <r>     4.8253     6.1132    34.3763 </r>
       <r>     4.9146     5.4553    34.8630 </r>
       <r>     5.0038     5.5426    35.3574 </r>
       <r>     5.0930     4.9045    35.7949 </r>
       <r>     5.1822     4.4925    36.1957 </r>
       <r>     5.2714     5.3355    36.6716 </r>
       <r>     5.3606     7.0859    37.3037 </r>
       <r>     5.4498     7.5887    37.9807 </r>
       <r>     5.5390     6.4096    38.5524 </r>
       <r>     5.6282     5.4891    39.0421 </r>
       <r>     5.7174     6.3743    39.6107 </r>
       <r>     5.8066     7.0744    40.2418 </r>
       <r>     5.8958     6.4161    40.8142 </r>
       <r>     5.9850     5.8349    41.3347 </r>
       <r>     6.0742     5.3869    41.8152 </r>
       <r>     6.1634     4.3287    42.2014 </r>
       <r>     6.2526     3.9962    42.5579 </r>
       <r>     6.3418     4.7819    42.9844 </r>
       <r>     6.4311     4.5006    43.3859 </r>
       <r>     6.5203     3.3091    43.6811 </r>
       <r>     6.6095     2.8497    43.9353 </r>
       <r>     6.6987     3.7655    44.2712 </r>
       <r>     6.7879     3.5523    44.5881 </r>
       <r>     6.8771     3.1717    44.8710 </r>
       <r>     6.9663     2.8684    45.1269 </r>
       <r>     7.0555     2.9934    45.3939 </r>
       <r>     7.1447     4.7084    45.8140 </r>
       <r>     7.2339     6.1010    46.3582 </r>
       <r>     7.3231     6.4496    46.9335 </r>
       <r>     7.4123     5.5177    47.4258 </r>
       <r>     7.5015     3.6179    47.7485 </r>
       <r>     7.5907     1.9976    47.9267 </r>
       <r>     7.6799     0.6531    47.9850 </r>
       <r>     7.7691     0.1486    47.9982 </r>
       <r>     7.8583     0.0193    47.9999 </r>
       <r>     7.9476     0.0007    48.0000 </r>
       <r>     8.0368     0.0000    48.0000 </r>
       <r>     8.1260     0.0000    48.0000 </r>
       <r>     8.2152     0.0000    48.0000 </r>
       <r>     8.3044     0.0000    48.0000 </r>
       <r>     8.3936     0.0000    48.0000 </r>
       <r>     8.4828     0.0000    48.0000 </r>
       <r>     8.5720     0.0000    48.0000 </r>
       <r>     8.6612     0.0000    48.0000 </r>
       <r>     8.7504     0.0000    48.0000 </r>
       <r>     8.8396     0.0000    48.0000 </r>
       <r>     8.9288     0.0000    48.0000 </r>
       <r>     9.0180     0.0000    48.0000 </r>
       <r>     9.1072     0.0000    48.0000 </r>
       <r>     9.1964     0.0000    48.0000 </r>
       <r>     9.2856     0.0000    48.0000 </r>
       <r>     9.3748     0.0000    48.0000 </r>
       <r>     9.4641     0.0000    48.0000 </r>
       <r>     9.5533     0.0000    48.0000 </r>
       <r>     9.6425     0.0000    48.0000 </r>
       <r>     9.7317     0.0000    48.0000 </r>
       <r>     9.8209     0.0000    48.0000 </r>
       <r>     9.9101     0.0000    48.0000 </r>
       <r>     9.9993     0.0000    48.0000 </r>
       <r>    10.0885     0.0000    48.0000 </r>
       <r>    10.1777     0.0000    48.0000 </r>
       <r>    10.2669     0.0000    48.0000 </r>
       <r>    10.3561     0.0000    48.0000 </r>
       <r>    10.4453     0.0002    48.0000 </r>
       <r>    10.5345     0.0102    48.0009 </r>
       <r>    10.6237     0.1644    48.0156 </r>
       <r>    10.7129     0.8289    48.0895 </r>
       <r>    10.8021     1.4440    48.2183 </r>
       <r>    10.8913     1.2666    48.3313 </r>
       <r>    10.9806     1.6886    48.4820 </r>
       <r>    11.0698     2.3401    48.6907 </r>
       <r>    11.1590     2.3130    48.8970 </r>
       <r>    11.2482     2.6105    49.1299 </r>
       <r>    11.3374     3.1604    49.4118 </r>
       <r>    11.4266     4.5106    49.8142 </r>
       <r>    11.5158     5.6563    50.3188 </r>
       <r>    11.6050     4.8618    50.7525 </r>
       <r>    11.6942     3.0863    51.0278 </r>
       <r>    11.7834     2.0716    51.2126 </r>
       <r>    11.8726     1.2565    51.3247 </r>
       <r>    11.9618     2.1550    51.5169 </r>
       <r>    12.0510     4.3952    51.9090 </r>
       <r>    12.1402     5.3128    52.3830 </r>
       <r>    12.2294     4.8107    52.8121 </r>
       <r>    12.3186     3.1368    53.0919 </r>
       <r>    12.4078     2.8968    53.3503 </r>
       <r>    12.4971     4.2781    53.7320 </r>
       <r>    12.5863     4.6408    54.1460 </r>
       <r>    12.6755     4.3058    54.5301 </r>
       <r>    12.7647     4.4700    54.9288 </r>
       <r>    12.8539     4.6668    55.3451 </r>
       <r>    12.9431     5.4123    55.8279 </r>
       <r>    13.0323     6.2572    56.3861 </r>
       <r>    13.1215     4.4657    56.7845 </r>
       <r>    13.2107     3.1016    57.0612 </r>
       <r>    13.2999     3.2763    57.3534 </r>
       <r>    13.3891     2.9462    57.6162 </r>
       <r>    13.4783     3.0221    57.8858 </r>
       <r>    13.5675     4.3472    58.2736 </r>
       <r>    13.6567     4.4000    58.6661 </r>
       <r>    13.7459     3.4053    58.9699 </r>
       <r>    13.8351     3.9357    59.3210 </r>
       <r>    13.9243     4.2377    59.6990 </r>
       <r>    14.0136     3.6469    60.0243 </r>
       <r>    14.1028     3.8105    60.3643 </r>
       <r>    14.1920     4.2212    60.7408 </r>
       <r>    14.2812     4.5326    61.1452 </r>
       <r>    14.3704     4.6311    61.5583 </r>
       <r>    14.4596     4.5277    61.9622 </r>
       <r>    14.5488     4.6078    62.3732 </r>
       <r>    14.6380     4.6927    62.7918 </r>
       <r>    14.7272     5.0800    63.2450 </r>
       <r>    14.8164     3.8599    63.5893 </r>
       <r>    14.9056     2.3171    63.7960 </r>
       <r>    14.9948     1.4171    63.9224 </r>
       <r>    15.0840     0.4816    63.9654 </r>
       <r>    15.1732     0.1492    63.9787 </r>
       <r>    15.2624     0.1647    63.9934 </r>
       <r>    15.3516     0.0671    63.9994 </r>
       <r>    15.4408     0.0067    64.0000 </r>
       <r>    15.5301     0.0002    64.0000 </r>
       <r>    15.6193     0.0000    64.0000 </r>
       <r>    15.7085     0.0000    64.0000 </r>
       <r>    15.7977     0.0000    64.0000 </r>
       <r>    15.8869     0.0000    64.0000 </r>
       <r>    15.9761     0.0000    64.0000 </r>
       <r>    16.0653     0.0000    64.0000 </r>
       <r>    16.1545     0.0000    64.0000 </r>
       <r>    16.2437     0.0000    64.0000 </r>
       <r>    16.3329     0.0000    64.0000 </r>
       <r>    16.4221     0.0000    64.0000 </r>
      </set>
     </set>
    </array>
   </total>
  </dos>
 </calculation>
 <structure name="finalpos" >
  <crystal>
   <varray name="basis" >
    <v>       5.40345231       0.01419918      -0.01828798 </v>
    <v>       2.71397382       4.68842978      -0.02388673 </v>
    <v>       2.68860528       1.55157548       5.03149486 </v>
   </varray>
   <i name="volume">    127.62538828 </i>
   <varray name="rec_basis" >
    <v>       0.18512674      -0.10749873      -0.06577376 </v>
    <v>      -0.00078212       0.21341061      -0.06539207 </v>
    <v>       0.00066917       0.00062243       0.19819858 </v>
   </varray>
  </crystal>
  <varray name="positions" >
   <v>       0.00322141       0.67357921       0.98998684 </v>
   <v>       0.49074790       0.83536698       0.50731941 </v>
   <v>       0.16838619       0.49915622       0.50846631 </v>
   <v>       0.66339513       0.33161658       0.00020724 </v>
   <v>       0.34407688       0.00214996       0.98380360 </v>
   <v>       0.83733282       0.16245101       0.49909292 </v>
   <v>       0.51817808       0.20146250       0.39084581 </v>
   <v>       0.36203311       0.70700742       0.86747040 </v>
   <v>       0.03569535       0.39565514       0.87420963 </v>
   <v>       0.22635770       0.85457648       0.37743993 </v>
   <v>       0.87423869       0.56344319       0.37045732 </v>
   <v>       0.72633673       0.02353529       0.88070057 </v>
  </varray>
 </structure>
</modeling>
