<?xml version="1.0" ?><modeling><calculation><energy>
   <i name="e_fr_energy">    -18.66586604 </i>
   <i name="e_wo_entrp">    -18.66517475 </i>
   <i name="e_0_energy">     -0.00207385 </i>
  </energy>
  <varray name="forces">
   <v>      -0.00986731       0.00422342      -0.00422342 </v>
   <v>       0.01296322      -0.00470867       0.00470867 </v>
   <v>      -0.00150063      -0.00244866       0.00244866 </v>
   <v>      -0.00516979       0.00836198      -0.00836198 </v>
   <v>       0.01157336      -0.00201300       0.00201300 </v>
   <v>      -0.00799885      -0.00341508       0.00341508 </v>
  </varray>
  <varray name="stress">
   <v>       0.98553370       0.02397190      -0.02397190 </v>
   <v>       0.02397138       1.23444882      -0.57791219 </v>
   <v>      -0.02397138      -0.57791219       1.23444882 </v>
  </varray>
  <structure name="finalpos">
  <crystal>
   <varray name="basis">
    <v>       0.00000000      -2.03439548      -2.03439548 </v>
    <v>       1.89398847       4.14453486      -2.11013938 </v>
    <v>       5.62089338      -2.09610635       4.13050183 </v>
   </varray>
   <i name="volume">     95.51482943 </i>
   <varray name="rec_basis">
    <v>       0.13292106      -0.20608309      -0.28546342 </v>
    <v>       0.13262217       0.11972089      -0.11972089 </v>
    <v>       0.13321995      -0.04034056       0.04034056 </v>
   </varray>
  </crystal>
  <varray name="positions">
   <v>       0.35258741       0.03931343       0.66586139 </v>
   <v>       0.14902194       0.46230526       0.83573861 </v>
   <v>       0.96202770       0.95727775       0.96677766 </v>
   <v>       0.67645543       0.01294484       0.33996603 </v>
   <v>       0.53702950       0.54170882       0.53235018 </v>
   <v>       0.82287801       0.48644990       0.15930613 </v>
  </varray>
 </structure>
<array name="atomtypes">
   <dimension dim="1">type</dimension>
   <field type="int">atomspertype</field>
   <field type="string">element</field>
   <field>mass</field>
   <field>valence</field>
   <field type="string">pseudopotential</field>
   <set>
    <rc><c>   2</c><c>Cu</c><c>     63.54600000</c><c>     11.00000000</c><c>  PAW_PBE Cu 22Jun2005                  </c></rc>
    <rc><c>   3</c><c>Ag</c><c>    107.86800000</c><c>     11.00000000</c><c>  PAW_PBE Ag 02Apr2005                  </c></rc>
    <rc><c>   1</c><c>Au</c><c>    196.96600000</c><c>     11.00000000</c><c>  PAW_PBE Au 04Oct2007                  </c></rc>
   </set>
  </array>
 <array name="atoms">
   <dimension dim="1">ion</dimension>
   <field type="string">element</field>
   <field type="int">atomtype</field>
   <set>
    <rc><c>Cu</c><c>   1</c></rc>
    <rc><c>Cu</c><c>   1</c></rc>
    <rc><c>Ag</c><c>   2</c></rc>
    <rc><c>Ag</c><c>   2</c></rc>
    <rc><c>Ag</c><c>   2</c></rc>
    <rc><c>Au</c><c>   3</c></rc>
   </set>
  </array>
  </calculation></modeling>
