<?xml version="1.0" ?><modeling><calculation><energy>
   <i name="e_fr_energy">    -13.20177922 </i>
   <i name="e_wo_entrp">    -13.20183784 </i>
   <i name="e_0_energy">      0.00017588 </i>
  </energy>
  <varray name="forces">
   <v>      -0.01817572      -0.00073347       0.00073347 </v>
   <v>       0.01817572       0.00073347      -0.00073347 </v>
   <v>       0.00000000       0.00000000       0.00000000 </v>
   <v>       0.00000000       0.00000000       0.00000000 </v>
  </varray>
  <varray name="stress">
   <v>       1.65336713       0.00144691      -0.00144691 </v>
   <v>       0.00144725       0.19980027      -0.16765002 </v>
   <v>      -0.00144725      -0.16765002       0.19980027 </v>
  </varray>
  <structure name="finalpos">
  <crystal>
   <varray name="basis">
    <v>       0.00000000      -1.99553366      -1.99553366 </v>
    <v>      -1.85869540      -1.85722333       3.85275699 </v>
    <v>      -4.02358891       2.00522747      -2.00522747 </v>
   </varray>
   <i name="volume">     60.72174988 </i>
   <varray name="rec_basis">
    <v>      -0.06589894      -0.31667430      -0.18444479 </v>
    <v>      -0.13179788      -0.13222951       0.13222951 </v>
    <v>      -0.18765036       0.06108337      -0.06108337 </v>
   </varray>
  </crystal>
  <varray name="positions">
   <v>       0.25136031       0.50272061       0.75184686 </v>
   <v>       0.74863969       0.49727939       0.24815314 </v>
   <v>       0.50000000       0.00000000       0.50000000 </v>
   <v>       0.00000000       0.00000000       0.00000000 </v>
  </varray>
 </structure>
<array name="atomtypes">
   <dimension dim="1">type</dimension>
   <field type="int">atomspertype</field>
   <field type="string">element</field>
   <field>mass</field>
   <field>valence</field>
   <field type="string">pseudopotential</field>
   <set>
    <rc><c>   2</c><c>Cu</c><c>     63.54600000</c><c>     11.00000000</c><c>  PAW_PBE Cu 22Jun2005                  </c></rc>
    <rc><c>   1</c><c>Ag</c><c>    107.86800000</c><c>     11.00000000</c><c>  PAW_PBE Ag 02Apr2005                  </c></rc>
    <rc><c>   1</c><c>Au</c><c>    196.96600000</c><c>     11.00000000</c><c>  PAW_PBE Au 04Oct2007                  </c></rc>
   </set>
  </array>
 <array name="atoms">
   <dimension dim="1">ion</dimension>
   <field type="string">element</field>
   <field type="int">atomtype</field>
   <set>
    <rc><c>Cu</c><c>   1</c></rc>
    <rc><c>Cu</c><c>   1</c></rc>
    <rc><c>Ag</c><c>   2</c></rc>
    <rc><c>Au</c><c>   3</c></rc>
   </set>
  </array>
  </calculation></modeling>
